Workbook

Sheet README
B1: ICICI BANK | RECESSION BANKING SIMULATION MODEL
B2: CIA 3 – Banking Simulation (20% weightage) | Opening position: ICICI Bank audited standalone results, 31 March 2026 | 8 quarterly rounds under a recession
B4: HOW TO USE
B5: 1. Market | C5: Recession conditions for each round (repo rate, default stress, system growth, fee activity, treasury). Replace the blue cells with the conditions the faculty announces in class.
B6: 2. Decisions | C6: Our management decisions for each quarter: loan growth by segment, pricing, deposit rates, marketing, collections, underwriting, provisioning and dividend. Every number on every other sheet recalculates from these two sheets.
B7: 3. Engine sheets | C7: Loan_Book → NPA_Provisions → Funding → P&L → Balance_Sheet → Capital_RAROC. Each quarter rolls forward from the previous quarter's closing balance.
B8: 4. Scorecard sheets | C8: Segment_RAROC (where capital earns the most), Market_Share, Customer_Survey (simulated survey + questionnaire) and Dashboard (one-page summary).
B9: 5. Decision_Log | C9: What happened each round, what we decided and why – this is what we narrate in class.
B11: COLOUR CODE
B12: Blue text, yellow fill | C12: Input / decision lever – safe to change
B13: Blue text, no fill | C13: Sourced actual (ICICI filings / RBI) or estimate – see Sources sheet
B14: Black text | C14: Formula – do not overwrite
B16: DATA LABELS
B17: A = Actual | C17: ICICI Bank reported standalone figure (FY25, FY26)
B18: E = Estimate | C18: Balance-sheet split or segment mix estimated from ICICI disclosures so that totals tie to reported figures
B19: S = Simulation | C19: All Y1–Y2 figures are fictional outcomes of the recession scenario and our decisions; they are NOT ICICI Bank results
B21: UNITS | C21: ₹ crore unless stated. Quarterly ratios that are annualised say so. Sim Year columns: flows = sum of 4 quarters; balances = year-end.
B22: INTEGRITY CHECKS | C22: Dashboard bottom rows: balance sheet must balance (0) and annual PAT must equal the sum of quarters (0).

Sheet Dashboard
A1: ICICI BANK | SIMULATION SCORECARD
A2: The four metrics the brief grades on – profitability, customer satisfaction, market share and RAROC – plus capital and asset quality.
B4: Metric | C4: FY2025 (A) | D4: FY2026 (A) | E4: Sim Year 1 | F4: Sim Year 2 | G4: Y2 vs FY26 | H4: Comment
B5: PROFITABILITY
B6: Net interest income | C6: =Baseline!C6 -> 81164 | D6: =Baseline!D6 -> 88075 | E6: ='P&L'!L9 -> 91700.035 | F6: ='P&L'!M9 -> 95855.518 | G6: =IFERROR(F6/D6-1,"") -> 0.088339682
B7: Pre-provision operating profit | C7: =Baseline!C9 -> 67235.318 | D7: =Baseline!D9 -> 71599 | E7: ='P&L'!L16 -> 70067.791 | F7: ='P&L'!M16 -> 73105.001 | G7: =IFERROR(F7/D7-1,"") -> 0.02103383
B8: Provisions | C8: =Baseline!C10 -> 4683 | D8: =Baseline!D10 -> 5380 | E8: ='P&L'!L17 -> 25351.515 | F8: ='P&L'!M17 -> 16259.786 | G8: =IFERROR(F8/D8-1,"") -> 2.0222651
B9: Net profit (PAT) | C9: =Baseline!C13 -> 47227 | D9: =Baseline!D13 -> 50147 | E9: ='P&L'!L21 -> 33461.189 | F9: ='P&L'!M21 -> 42537.274 | G9: =IFERROR(F9/D9-1,"") -> -0.15174837
B10: Return on assets | D10: ='P&L'!C25 -> 0.022333359 | E10: ='P&L'!L25 -> 0.013526606 | F10: ='P&L'!M25 -> 0.015768183 | G10: =IFERROR((F10-D10)*10000,"") -> -65.651756
B11: Return on equity | D11: ='P&L'!C26 -> 0.1514322 | E11: ='P&L'!L26 -> 0.091738181 | F11: ='P&L'!M26 -> 0.1077188 | G11: =IFERROR((F11-D11)*10000,"") -> -437.13398
B12: Net interest margin | C12: =Baseline!C24 -> 0.0432 | D12: ='P&L'!C23 -> 0.039699693 | E12: ='P&L'!L23 -> 0.039490263 | F12: ='P&L'!M23 -> 0.037818436 | G12: =IFERROR((F12-D12)*10000,"") -> -18.812576 | H12: FY25/FY26 reported 4.32%; model basis = avg earning assets
B13: Cost-to-income | C13: =Baseline!C8/(Baseline!C6+Baseline!C7) -> 0.38658003 | D13: ='P&L'!C24 -> 0.39748218 | E13: ='P&L'!L24 -> 0.42308128 | F13: ='P&L'!M24 -> 0.4196368 | G13: =IFERROR((F13-D13)*10000,"") -> 221.54615
B14: RISK-ADJUSTED RETURN
B15: RAROC | D15: =Capital_RAROC!C28 -> 0.18244505 | E15: =Capital_RAROC!L28 -> 0.14370486 | F15: =Capital_RAROC!M28 -> 0.1508965 | G15: =IFERROR((F15-D15)*10000,"") -> -315.48546 | H15: Hurdle 14%
B16: Economic value added (₹ cr) | D16: =Capital_RAROC!C31 -> 10645.716 | E16: =Capital_RAROC!L31 -> 955.49718 | F16: =Capital_RAROC!M31 -> 2954.065 | G16: =IFERROR(F16/D16-1,"") -> -0.72251139
B17: ASSET QUALITY
B18: Gross NPA ratio | C18: =Baseline!C19 -> 0.0167 | D18: =NPA_Provisions!C24 -> 0.014 | E18: =NPA_Provisions!L24 -> 0.027383747 | F18: =NPA_Provisions!M24 -> 0.025909369 | G18: =IFERROR((F18-D18)*10000,"") -> 119.09369
B19: Net NPA ratio | C19: =Baseline!C20 -> 0.0039 | D19: =NPA_Provisions!C25 -> 0.0034243391 | E19: =NPA_Provisions!L25 -> 0.0061559103 | F19: =NPA_Provisions!M25 -> 0.0058176314 | G19: =IFERROR((F19-D19)*10000,"") -> 23.932923
B20: Credit cost | D20: =Baseline!D10/AVERAGE(Baseline!C17,Baseline!D17) -> 0.0037159072 | E20: =NPA_Provisions!L32 -> 0.015886087 | F20: =NPA_Provisions!M32 -> 0.0096709814 | G20: =IFERROR((F20-D20)*10000,"") -> 59.550742
B21: Contingency buffer left (₹ cr) | D21: =NPA_Provisions!C31 -> 13100 | E21: =NPA_Provisions!L31 -> 10100 | F21: =NPA_Provisions!M31 -> 9600 | G21: =IFERROR(F21/D21-1,"") -> -0.26717557
B22: CAPITAL & LIQUIDITY
B23: CET-1 ratio | C23: =Baseline!C23 -> 0.1594 | D23: =Capital_RAROC!C18 -> 0.1635 | E23: =Capital_RAROC!L18 -> 0.1681383 | F23: =Capital_RAROC!M18 -> 0.17220977 | G23: =IFERROR((F23-D23)*10000,"") -> 87.097726 | H23: Minimum 8.20%
B24: Total capital adequacy | C24: =Baseline!C22 -> 0.1655 | D24: =Capital_RAROC!C19 -> 0.1718 | E24: =Capital_RAROC!L19 -> 0.17611046 | F24: =Capital_RAROC!M19 -> 0.17967446 | G24: =IFERROR((F24-D24)*10000,"") -> 78.744594 | H24: Minimum 11.70%
B25: Loan-to-deposit ratio | C25: =Baseline!C17/Baseline!C16 -> 0.83321493 | D25: =Funding!C18 -> 0.86585944 | E25: =Funding!L18 -> 0.82429357 | F25: =Funding!M18 -> 0.80002245 | G25: =IFERROR((F25-D25)*10000,"") -> -658.36989
B26: CASA ratio | D26: =Funding!C7 -> 0.414 | E26: =Funding!L7 -> 0.4005 | F26: =Funding!M7 -> 0.41075 | G26: =IFERROR((F26-D26)*10000,"") -> -32.5
B27: GROWTH & MARKET SHARE
B28: Deposits | C28: =Baseline!C16 -> 1610348 | D28: =Funding!C6 -> 1794625 | E28: =Funding!L6 -> 1975132.5 | F28: =Funding!M6 -> 2185701.6 | G28: =IFERROR(F28/D28-1,"") -> 0.21791551
B29: Net advances | C29: =Baseline!C17 -> 1341766 | D29: =Loan_Book!C11 -> 1553893 | E29: =Loan_Book!L11 -> 1628089 | F29: =Loan_Book!M11 -> 1748610.4 | G29: =IFERROR(F29/D29-1,"") -> 0.12530938
B30: Deposit market share | D30: =Market_Share!C7 -> 0.068419014 | E30: =Market_Share!L7 -> 0.069091439 | F30: =Market_Share!M7 -> 0.069605934 | G30: =IFERROR((F30-D30)*10000,"") -> 11.8692
B31: Credit market share | D31: =Market_Share!C10 -> 0.076240766 | E31: =Market_Share!L10 -> 0.076619541 | F31: =Market_Share!M10 -> 0.077141201 | G31: =IFERROR((F31-D31)*10000,"") -> 9.0043515
B32: CUSTOMER
B33: Customer satisfaction index (simulated survey) | E33: =AVERAGE(Customer_Survey!C43:F43) -> 0.803 | F33: =AVERAGE(Customer_Survey!G43:J43) -> 0.8015 | H33: Average of four rounds
B34: Net Promoter Score (simulated survey) | E34: =AVERAGE(Customer_Survey!C41:F41) -> 44.5 | F34: =AVERAGE(Customer_Survey!G41:J41) -> 46
B35: MODEL INTEGRITY CHECKS (should all be 0)
B36: Balance sheet check | D36: =Balance_Sheet!C19 -> 0 | E36: =Balance_Sheet!L19 -> 0 | F36: =Balance_Sheet!M19 -> 0
B37: PAT annual vs sum of quarters | E37: =ROUND('P&L'!L21-SUM('P&L'!D21:G21),2) -> 0 | F37: =ROUND('P&L'!M21-SUM('P&L'!H21:K21),2) -> 0
B38: GNPA roll-forward check | E38: =ROUND(NPA_Provisions!G18-(NPA_Provisions!C18+NPA_Provisions!L15+NPA_Provisions!L16+NPA_Provisions!L17),2) -> 0 | F38: =ROUND(NPA_Provisions!K18-(NPA_Provisions!G18+NPA_Provisions!M15+NPA_Provisions!M16+NPA_Provisions!M17),2) -> 0

Sheet Decision_Log
A1: DECISION LOG | WHAT HAPPENED, WHAT WE DID, WHY
B3: Round | C3: Market condition | D3: Our decision | E3: Why | F3: PAT (₹ cr) | G3: GNPA
B4: Round 1 Y1 Q1 | C4: Downturn begins: GDP slows to 4.8%, defaults 1.4× normal, fee activity −5%. | D4: Start defensively: shrink unsecured retail 1%, tighten underwriting 5%, top up contingency buffer by ₹1,000 cr, launch salary-account and 'safe bank' campaign (₹300 cr). | E4: Act before NPAs show up in the numbers – buffers are cheapest to build while profits are still high. | F4: ='P&L'!D21 -> 9682.0496 | G4: =NPA_Provisions!D24 -> 0.015595785
B5: Round 2 Y1 Q2 | C5: RBI cuts repo to 5.00%; defaults 2.0×; CASA starts leaking into FDs. | D5: Add 25 bp risk premium on unsecured/SME, pay 10 bp FD premium, raise collections spend to ₹250 cr, pay the ₹12/share dividend already declared. | E5: Price risk honestly, lock in stable deposits, and honour the commitment to shareholders while capital is ample. | F5: ='P&L'!E21 -> 8057.3041 | G5: =NPA_Provisions!E24 -> 0.018723289
B6: Round 3 Y1 Q3 | C6: Recession deepens: GDP 2.2%, defaults 2.6×, recoveries weaken. Our RAROC slips below the 14% hurdle. | D6: Cut unsecured book 3%, tighten underwriting 15%, risk premium to 50 bp, raise PCR to 77%, release ₹1,500 cr of contingency buffer. | E6: Segment RAROC shows unsecured and rural lose the most capital value under stress – shrink them; the buffer exists for exactly this moment. | F6: ='P&L'!F21 -> 8027.6272 | G6: =NPA_Provisions!F24 -> 0.022870441
B7: Round 4 Y1 Q4 | C7: Trough: defaults peak at 3.0× normal, credit demand almost flat. | D7: Release ₹3,000 cr buffer, raise PCR to 78%, keep growing secured retail (+1.5%) and AAA/AA corporate (+2%), hold core cost growth at 0.5%. | E7: Protect capital and keep lending to the strongest borrowers; CET-1 stays above 16.5%, so we can absorb losses without stopping good lending. | F7: ='P&L'!G21 -> 7694.2082 | G7: =NPA_Provisions!G24 -> 0.027383747
B8: Round 5 Y2 Q1 | C8: Early recovery: GDP 2.5%, defaults easing to 2.7×; GNPA still rising. | D8: Release ₹2,000 cr more, keep collections at ₹250 cr, restart SME (+1%) and rural (+0.5%) growth. | E8: Stress is past its peak; position the book for the upturn without loosening underwriting. | F8: ='P&L'!H21 -> 8863.2433 | G8: =NPA_Provisions!H24 -> 0.029797357
B9: Round 6 Y2 Q2 | C9: Stabilising: defaults 2.2×, credit demand returns; RAROC back above hurdle. | D9: Cut dividend to ₹10/share, halve the risk premium to 25 bp, hold unsecured lending flat, step up marketing to ₹350 cr. | E9: Retain capital for recovery growth and pass lower expected loss back to customers. | F9: ='P&L'!I21 -> 9570.4686 | G9: =NPA_Provisions!I24 -> 0.029984478
B10: Round 7 Y2 Q3 | C10: Recovery: GDP 4.5%, repo stable, fees recover. | D10: Grow every segment, end the FD premium, rebuild contingency buffer by ₹500 cr. | E10: Rebuild the shock absorber for the next downturn while gaining market share. | F10: ='P&L'!J21 -> 11475.18 | G10: =NPA_Provisions!J24 -> 0.028269751
B11: Round 8 Y2 Q4 | C11: Normalisation: GDP 5.5%, RBI hikes 25 bp. | D11: Full growth in secured retail (+2.5%), SME (+2.5%) and corporate; rebuild buffer by ₹1,000 cr. | E11: Return to share gains with a safer, more secured loan mix than before the recession. | F11: ='P&L'!K21 -> 12628.382 | G11: =NPA_Provisions!K24 -> 0.025909369

Sheet Market
A1: MARKET CONDITIONS | RECESSION SCENARIO (INPUTS)
A2: Blue/yellow cells are the economic environment for each round. Replace with the conditions announced in class; everything downstream recalculates.
D3: Round 1 | E3: Round 2 | F3: Round 3 | G3: Round 4 | H3: Round 5 | I3: Round 6 | J3: Round 7 | K3: Round 8
B4: Particulars | C4: Opening (Mar-26) | D4: Y1 Q1 | E4: Y1 Q2 | F4: Y1 Q3 | G4: Y1 Q4 | H4: Y2 Q1 | I4: Y2 Q2 | J4: Y2 Q3 | K4: Y2 Q4 | L4: Basis / note
B5: ECONOMY & POLICY
B6: Real GDP growth (annualised, %) | C6: 0.065 | D6: 0.048 | E6: 0.035 | F6: 0.022 | G6: 0.018 | H6: 0.025 | I6: 0.035 | J6: 0.045 | K6: 0.055 | N6: S – recession troughs in Y1 Q4, recovery through Y2
B7: RBI repo rate (end of quarter) | C7: 0.0525 | D7: 0.0525 | E7: 0.05 | F7: 0.0475 | G7: 0.045 | H7: 0.045 | I7: 0.045 | J7: 0.045 | K7: 0.0475 | N7: S – RBI eases 75 bp into the downturn, hikes 25 bp in recovery
B8: Change in repo vs opening | D8: =D7-$C$7 -> 0 | E8: =E7-$C$7 -> -0.0025 | F8: =F7-$C$7 -> -0.005 | G8: =G7-$C$7 -> -0.0075 | H8: =H7-$C$7 -> -0.0075 | I8: =I7-$C$7 -> -0.0075 | J8: =J7-$C$7 -> -0.0075 | K8: =K7-$C$7 -> -0.005
B9: CREDIT & DEPOSIT MARKET
B10: Default stress multiplier (× normal slippage rates) | C10: 1 | D10: 1.4 | E10: 2 | F10: 2.6 | G10: 3 | H10: 2.7 | I10: 2.2 | J10: 1.7 | K10: 1.4 | N10: S – job losses & weaker cash flows lift fresh NPAs; peaks at 3.0× normal
B11: Recovery environment index (1 = normal) | C11: 1 | D11: 0.95 | E11: 0.85 | F11: 0.75 | G11: 0.7 | H11: 0.75 | I11: 0.85 | J11: 0.95 | K11: 1 | N11: S – collateral values and borrower capacity fall in recession
B12: System deposit growth (quarterly) | D12: 0.025 | E12: 0.022 | F12: 0.02 | G12: 0.02 | H12: 0.021 | I12: 0.023 | J12: 0.025 | K12: 0.026 | N12: S – flight to safety keeps deposits growing
B13: System credit growth (quarterly) | D13: 0.02 | E13: 0.015 | F13: 0.01 | G13: 0.008 | H13: 0.01 | I13: 0.014 | J13: 0.018 | K13: 0.022 | N13: S – loan demand collapses then recovers
B14: CASA ratio drift (pp per quarter, market-driven) | D14: -0.004 | E14: -0.006 | F14: -0.006 | G14: -0.004 | H14: -0.002 | I14: 0 | J14: 0.002 | K14: 0.003 | N14: S – savers move from CASA to term deposits
B15: Fee activity index (1 = FY26 run-rate) | C15: 1 | D15: 0.95 | E15: 0.9 | F15: 0.86 | G15: 0.84 | H15: 0.87 | I15: 0.92 | J15: 0.96 | K15: 1 | N15: S – fewer disbursements, card spends and distribution fees
B16: Treasury gains / (losses) on bond book (₹ cr) | D16: 400 | E16: 900 | F16: 1100 | G16: 700 | H16: 300 | I16: 200 | J16: 100 | K16: -200 | N16: S – falling yields create mark-to-market gains
B18: BEHAVIOURAL ELASTICITIES (CONSTANTS)
B19: Share of loan book repricing with repo (floating EBLR/MCLR) | C19: 0.6 | N19: E – external-benchmark loans reprice within a quarter
B20: Term-deposit rate pass-through of repo change | C20: 0.45 | N20: E – term deposits reprice slowly
B21: CASA (savings) rate pass-through of repo change | C21: 0.1 | N21: E
B22: Investment-book yield pass-through of repo change | C22: 0.35 | N22: E – only new purchases reprice
B23: Extra deposit growth per 10 bp term-deposit premium (per qtr) | C23: 0.0012 | N23: E
B24: Extra deposit growth per ₹100 cr marketing (per qtr) | C24: 0.0004 | N24: E
B25: CASA uplift per ₹100 cr marketing (pp per qtr) | C25: 0.0005 | N25: E – salary & current-account campaigns
B26: Recovery uplift per ₹100 cr collections spend | C26: 0.02 | N26: E – early-warning teams, restructuring desks
B27: System deposits at 31 Mar 2026 (₹ cr) | C27: 26229916 | N27: A – RBI scheduled commercial banks, deposits from non-bank customers
B28: System bank credit at 31 Mar 2026 (₹ cr) | C28: 20600000 | N28: E – RBI fortnightly data, rounded
B29: Corporate tax rate | C29: 0.2517 | N29: A – statutory rate for banks under s.115BAA

Sheet Decisions
A1: OUR DECISIONS | QUARTERLY MANAGEMENT LEVERS (INPUTS)
A2: Team ICICI's choices each round across the four levers the brief asks for: investment, pricing, marketing and risk management.
D3: Round 1 | E3: Round 2 | F3: Round 3 | G3: Round 4 | H3: Round 5 | I3: Round 6 | J3: Round 7 | K3: Round 8
B4: Particulars | C4: FY26 base | D4: Y1 Q1 | E4: Y1 Q2 | F4: Y1 Q3 | G4: Y1 Q4 | H4: Y2 Q1 | I4: Y2 Q2 | J4: Y2 Q3 | K4: Y2 Q4 | L4: Basis / note
B5: 1. INVESTMENT STRATEGY – where we allocate the loan book (quarterly growth)
B6: Secured retail (mortgages, auto, gold) | D6: 0.02 | E6: 0.018 | F6: 0.015 | G6: 0.015 | H6: 0.018 | I6: 0.02 | J6: 0.023 | K6: 0.025 | N6: Lean into collateralised lending where losses are small
B7: Unsecured retail (personal loans, credit cards) | D7: -0.01 | E7: -0.025 | F7: -0.03 | G7: -0.02 | H7: -0.01 | I7: 0 | J7: 0.01 | K7: 0.015 | N7: Shrink the book most sensitive to job losses; restart in recovery
B8: Business banking & SME | D8: 0.02 | E8: 0.01 | F8: 0.005 | G8: 0.005 | H8: 0.01 | I8: 0.015 | J8: 0.02 | K8: 0.025 | N8: Keep cash-flow-backed working capital; slow term loans
B9: Rural & agri | D9: 0.01 | E9: 0 | F9: -0.005 | G9: 0 | H9: 0.005 | I9: 0.01 | J9: 0.015 | K9: 0.02 | N9: Pause, then return with priority-sector obligations
B10: Corporate & wholesale | D10: 0.025 | E10: 0.025 | F10: 0.02 | G10: 0.02 | H10: 0.02 | I10: 0.02 | J10: 0.02 | K10: 0.02 | N10: Grow with AAA/AA names as safe balance-sheet ballast
B11: 2. PRICING
B12: Risk premium on unsecured & SME loans (bp vs base) | D12: 0 | E12: 25 | F12: 50 | G12: 50 | H12: 50 | I12: 25 | J12: 0 | K12: 0 | N12: Price for higher expected loss; unwind in recovery
B13: Rate offer on secured retail (bp vs base) | D13: 0 | E13: -10 | F13: -10 | G13: -10 | H13: -10 | I13: -10 | J13: 0 | K13: 0 | N13: Small discount to win good-quality home-loan share
B14: Term-deposit rate premium vs market (bp) | D14: 0 | E14: 10 | F14: 15 | G14: 15 | H14: 10 | I14: 5 | J14: 0 | K14: 0 | N14: Pay a little more to lock in stable funding
B15: 3. MARKETING & CUSTOMER
B16: Incremental marketing & retention spend (₹ cr) | D16: 300 | E16: 350 | F16: 350 | G16: 300 | H16: 300 | I16: 350 | J16: 400 | K16: 400 | N16: Salary accounts, iMobile campaigns, 'safe bank' messaging
B17: Digital service & customer-support investment (₹ cr) | D17: 150 | E17: 150 | F17: 150 | G17: 150 | H17: 120 | I17: 120 | J17: 100 | K17: 100 | N17: Faster grievance resolution, EMI-relief journeys in-app
B18: 4. RISK MANAGEMENT
B19: Underwriting tightening (% cut in new slippage) | D19: 0.05 | E19: 0.1 | F19: 0.15 | G19: 0.15 | H19: 0.15 | I19: 0.12 | J19: 0.1 | K19: 0.08 | N19: Lower cut-offs, bureau + bank-statement checks, sector caps
B20: Collections & early-warning spend (₹ cr) | D20: 150 | E20: 250 | F20: 300 | G20: 300 | H20: 250 | I20: 200 | J20: 150 | K20: 100 | N20: Early-warning signals, restructuring desks, field collections
B21: Target provision coverage ratio (PCR) | C21: 0.758 | D21: 0.75 | E21: 0.76 | F21: 0.77 | G21: 0.78 | H21: 0.78 | I21: 0.78 | J21: 0.78 | K21: 0.78 | N21: Build coverage as NPAs rise
B22: Contingency provision: add / (release) (₹ cr) | D22: 1000 | E22: 500 | F22: -1500 | G22: -3000 | H22: -2000 | I22: 0 | J22: 500 | K22: 1000 | N22: Use part of the ₹13,100 cr buffer at the peak – that is what it was built for
B23: Core operating-cost growth (quarterly) | D23: 0.015 | E23: 0.01 | F23: 0.005 | G23: 0.005 | H23: 0.008 | I23: 0.01 | J23: 0.015 | K23: 0.018 | N23: Defer branch openings and hiring; protect technology
B24: CAPITAL
B25: Dividend paid (₹ cr) | D25: 0 | E25: 8568 | F25: 0 | G25: 0 | H25: 0 | I25: 7140 | J25: 0 | K25: 0 | N25: Y1: FY26 ₹12/share already declared (≈714 cr shares); Y2: cut to ₹10/share to protect capital

Sheet Baseline
A1: ICICI BANK | OPENING POSITION (ACTUALS)
A2: Standalone ₹ crore. FY25 and FY26 are reported figures (A) or derived from them (D); balance-sheet split marked E is an estimate that ties to reported totals.
B4: Line | C4: FY2025 | D4: FY2026 | E4: YoY % | F4: Basis
B5: PROFIT & LOSS
B6: Net interest income | C6: 81164 | D6: 88075 | E6: =IFERROR(D6/C6-1,"") -> 0.085148588 | F6: A – ICICI performance review FY25 / FY26
B7: Non-interest income (incl. treasury) | C7: =C9+C8-C6 -> 28443.318 | D7: =D9+D8-D6 -> 30758 | E7: =IFERROR(D7/C7-1,"") -> 0.081378766 | F7: D – PPOP + opex − NII
B8: Operating expenses | C8: 42372 | D8: 47234 | E8: =IFERROR(D8/C8-1,"") -> 0.11474559 | F8: A – results tables (Elite Wealth summary of filing)
B9: Pre-provision operating profit (PPOP) | C9: =C11+C10 -> 67235.318 | D9: 71599 | E9: =IFERROR(D9/C9-1,"") -> 0.064901636 | F9: FY26 A; FY25 D = PBT + provisions
B10: Provisions & contingencies | C10: 4683 | D10: 5380 | E10: =IFERROR(D10/C10-1,"") -> 0.14883622 | F10: A
B11: Profit before tax | C11: =C12+C13 -> 62552.318 | D11: =D9-D10 -> 66219 | E11: =IFERROR(D11/C11-1,"") -> 0.058617846 | F11: D
B12: Tax | C12: =C13/(1-0.245)*0.245 -> 15325.318 | D12: =D11-D13 -> 16072 | E12: =IFERROR(D12/C12-1,"") -> 0.048722129 | F12: FY25 E at 24.5% effective; FY26 D
B13: Net profit (PAT) | C13: 47227 | D13: 50147 | E13: =IFERROR(D13/C13-1,"") -> 0.061829038 | F13: A – ₹47,227 cr (FY25), ₹50,147 cr (FY26)
B14: BALANCE SHEET (31 March)
B15: Total assets | C15: 2118240 | D15: 2372531 | E15: =IFERROR(D15/C15-1,"") -> 0.12004825 | F15: A – standalone summary balance sheet
B16: Deposits | C16: 1610348 | D16: 1794625 | E16: =IFERROR(D16/C16-1,"") -> 0.11443303 | F16: A
B17: Net advances | C17: 1341766 | D17: 1553893 | E17: =IFERROR(D17/C17-1,"") -> 0.15809538 | F17: A
B18: ASSET QUALITY, CAPITAL & FRANCHISE
B19: Gross NPA ratio | C19: 0.0167 | D19: 0.014 | E19: =IFERROR((D19-C19)*10000,"") -> -27 | F19: A
B20: Net NPA ratio | C20: 0.0039 | D20: 0.0033 | E20: =IFERROR((D20-C20)*10000,"") -> -6 | F20: A
B21: Provision coverage ratio | D21: 0.758 | E21: =IFERROR((D21-C21)*10000,"") -> 7580 | F21: A
B22: Total capital adequacy (CRAR) | C22: 0.1655 | D22: 0.1718 | E22: =IFERROR((D22-C22)*10000,"") -> 63 | F22: A – regulatory minimum incl. buffers 11.70%
B23: CET-1 ratio | C23: 0.1594 | D23: 0.1635 | E23: =IFERROR((D23-C23)*10000,"") -> 41 | F23: A – regulatory minimum 8.20%
B24: Net interest margin | C24: 0.0432 | D24: 0.0432 | E24: =IFERROR((D24-C24)*10000,"") -> 0 | F24: A – reported NIM (Q4 FY26 4.32%)
B25: CASA ratio (period end) | D25: 0.414 | E25: =IFERROR((D25-C25)*10000,"") -> 4140 | F25: A
B26: Contingency provisions held | D26: 13100 | E26: =IFERROR(D26/C26-1,"") | F26: A – ₹131 bn (~0.9% of advances)
B27: Branches | C27: 6983 | D27: 7511 | E27: =IFERROR(D27/C27-1,"") -> 0.075612201 | F27: A
B28: Dividend per share (₹) | C28: 11 | D28: 12 | E28: =IFERROR(D28/C28-1,"") -> 0.090909091 | F28: A – FY26 ₹12 recommended
B30: Latest real context (not used in the model): Q2 FY27 (Jul–Sep 2026) standalone PAT ₹14,843 cr, NII ₹25,339 cr, NIM 4.18%, GNPA 1.20%. The recession in this model is a hypothetical classroom scenario.

Sheet Loan_Book
A1: LOAN BOOK & INTEREST INCOME FROM ADVANCES
A2: Net advances by segment. Opening mix is an estimate (E) from ICICI segment disclosures (retail 50.4% of loans at Mar-26); total ties to reported ₹15,53,893 cr.
B4: Particulars | C4: Mar-26 / FY26 (A) | D4: Y1 Q1 | E4: Y1 Q2 | F4: Y1 Q3 | G4: Y1 Q4 | H4: Y2 Q1 | I4: Y2 Q2 | J4: Y2 Q3 | K4: Y2 Q4 | L4: Sim Year 1 | M4: Sim Year 2 | N4: Basis / note
B5: CLOSING NET ADVANCES BY SEGMENT
B6: Secured retail (mortgages, auto, gold) | C6: =Baseline!D17*0.384 -> 596694.91 | D6: =C6*(1+Decisions!D6) -> 608628.81 | E6: =D6*(1+Decisions!E6) -> 619584.13 | F6: =E6*(1+Decisions!F6) -> 628877.89 | G6: =F6*(1+Decisions!G6) -> 638311.06 | H6: =G6*(1+Decisions!H6) -> 649800.66 | I6: =H6*(1+Decisions!I6) -> 662796.67 | J6: =I6*(1+Decisions!J6) -> 678040.99 | K6: =J6*(1+Decisions!K6) -> 694992.02 | L6: =G6 -> 638311.06 | M6: =K6 -> 694992.02 | N6: Opening = reported net advances × 38.4% (E); grows at Decisions row 6
B7: Unsecured retail (personal loans, cards) | C7: =Baseline!D17*0.12 -> 186467.16 | D7: =C7*(1+Decisions!D7) -> 184602.49 | E7: =D7*(1+Decisions!E7) -> 179987.43 | F7: =E7*(1+Decisions!F7) -> 174587.8 | G7: =F7*(1+Decisions!G7) -> 171096.05 | H7: =G7*(1+Decisions!H7) -> 169385.09 | I7: =H7*(1+Decisions!I7) -> 169385.09 | J7: =I7*(1+Decisions!J7) -> 171078.94 | K7: =J7*(1+Decisions!K7) -> 173645.12 | L7: =G7 -> 171096.05 | M7: =K7 -> 173645.12 | N7: Opening = reported net advances × 12.0% (E); grows at Decisions row 7
B8: Business banking & SME | C8: =Baseline!D17*0.194 -> 301455.24 | D8: =C8*(1+Decisions!D8) -> 307484.35 | E8: =D8*(1+Decisions!E8) -> 310559.19 | F8: =E8*(1+Decisions!F8) -> 312111.99 | G8: =F8*(1+Decisions!G8) -> 313672.55 | H8: =G8*(1+Decisions!H8) -> 316809.27 | I8: =H8*(1+Decisions!I8) -> 321561.41 | J8: =I8*(1+Decisions!J8) -> 327992.64 | K8: =J8*(1+Decisions!K8) -> 336192.45 | L8: =G8 -> 313672.55 | M8: =K8 -> 336192.45 | N8: Opening = reported net advances × 19.4% (E); grows at Decisions row 8
B9: Rural & agri | C9: =Baseline!D17*0.058 -> 90125.794 | D9: =C9*(1+Decisions!D9) -> 91027.052 | E9: =D9*(1+Decisions!E9) -> 91027.052 | F9: =E9*(1+Decisions!F9) -> 90571.917 | G9: =F9*(1+Decisions!G9) -> 90571.917 | H9: =G9*(1+Decisions!H9) -> 91024.776 | I9: =H9*(1+Decisions!I9) -> 91935.024 | J9: =I9*(1+Decisions!J9) -> 93314.049 | K9: =J9*(1+Decisions!K9) -> 95180.33 | L9: =G9 -> 90571.917 | M9: =K9 -> 95180.33 | N9: Opening = reported net advances × 5.8% (E); grows at Decisions row 9
B10: Corporate & wholesale | C10: =Baseline!D17*0.244 -> 379149.89 | D10: =C10*(1+Decisions!D10) -> 388628.64 | E10: =D10*(1+Decisions!E10) -> 398344.36 | F10: =E10*(1+Decisions!F10) -> 406311.24 | G10: =F10*(1+Decisions!G10) -> 414437.47 | H10: =G10*(1+Decisions!H10) -> 422726.22 | I10: =H10*(1+Decisions!I10) -> 431180.74 | J10: =I10*(1+Decisions!J10) -> 439804.36 | K10: =J10*(1+Decisions!K10) -> 448600.44 | L10: =G10 -> 414437.47 | M10: =K10 -> 448600.44 | N10: Opening = reported net advances × 24.4% (E); grows at Decisions row 10
B11: TOTAL NET ADVANCES | C11: =SUM(C6:C10) -> 1553893 | D11: =SUM(D6:D10) -> 1580371.3 | E11: =SUM(E6:E10) -> 1599502.2 | F11: =SUM(F6:F10) -> 1612460.8 | G11: =SUM(G6:G10) -> 1628089 | H11: =SUM(H6:H10) -> 1649746 | I11: =SUM(I6:I10) -> 1676858.9 | J11: =SUM(J6:J10) -> 1710231 | K11: =SUM(K6:K10) -> 1748610.4 | L11: =G11 -> 1628089 | M11: =K11 -> 1748610.4
B12: Loan growth (quarterly / annual) | D12: =D11/C11-1 -> 0.01704 | E12: =E11/D11-1 -> 0.012105266 | F12: =F11/E11-1 -> 0.0081017002 | G12: =G11/F11-1 -> 0.0096921405 | H12: =H11/G11-1 -> 0.013302081 | I12: =I11/H11-1 -> 0.016434605 | J12: =J11/I11-1 -> 0.019901521 | K12: =K11/J11-1 -> 0.022441058 | L12: =G11/C11-1 -> 0.047748485 | M12: =K11/G11-1 -> 0.074026254
B13: Unsecured retail share of book | C13: =C7/C11 -> 0.12 | D13: =D7/D11 -> 0.11680957 | E13: =E7/E11 -> 0.11252715 | F13: =F7/F11 -> 0.10827414 | G13: =G7/G11 -> 0.1050901 | H13: =H7/H11 -> 0.10267343 | I13: =I7/I11 -> 0.10101332 | J13: =J7/J11 -> 0.10003265 | K13: =K7/K11 -> 0.099304639 | L13: =G7/G11 -> 0.1050901 | M13: =K7/K11 -> 0.099304639
B14: AVERAGE BALANCES
B15: Avg – Secured retail (mortgages, auto, gold) | D15: =AVERAGE(C6,D6) -> 602661.86 | E15: =AVERAGE(D6,E6) -> 614106.47 | F15: =AVERAGE(E6,F6) -> 624231.01 | G15: =AVERAGE(F6,G6) -> 633594.47 | H15: =AVERAGE(G6,H6) -> 644055.86 | I15: =AVERAGE(H6,I6) -> 656298.66 | J15: =AVERAGE(I6,J6) -> 670418.83 | K15: =AVERAGE(J6,K6) -> 686516.51 | L15: =AVERAGE(D15:G15) -> 618648.45 | M15: =AVERAGE(H15:K15) -> 664322.47
B16: Avg – Unsecured retail (personal loans, cards) | D16: =AVERAGE(C7,D7) -> 185534.82 | E16: =AVERAGE(D7,E7) -> 182294.96 | F16: =AVERAGE(E7,F7) -> 177287.61 | G16: =AVERAGE(F7,G7) -> 172841.93 | H16: =AVERAGE(G7,H7) -> 170240.57 | I16: =AVERAGE(H7,I7) -> 169385.09 | J16: =AVERAGE(I7,J7) -> 170232.01 | K16: =AVERAGE(J7,K7) -> 172362.03 | L16: =AVERAGE(D16:G16) -> 179489.83 | M16: =AVERAGE(H16:K16) -> 170554.92
B17: Avg – Business banking & SME | D17: =AVERAGE(C8,D8) -> 304469.79 | E17: =AVERAGE(D8,E8) -> 309021.77 | F17: =AVERAGE(E8,F8) -> 311335.59 | G17: =AVERAGE(F8,G8) -> 312892.27 | H17: =AVERAGE(G8,H8) -> 315240.91 | I17: =AVERAGE(H8,I8) -> 319185.34 | J17: =AVERAGE(I8,J8) -> 324777.02 | K17: =AVERAGE(J8,K8) -> 332092.55 | L17: =AVERAGE(D17:G17) -> 309429.85 | M17: =AVERAGE(H17:K17) -> 322823.96
B18: Avg – Rural & agri | D18: =AVERAGE(C9,D9) -> 90576.423 | E18: =AVERAGE(D9,E9) -> 91027.052 | F18: =AVERAGE(E9,F9) -> 90799.484 | G18: =AVERAGE(F9,G9) -> 90571.917 | H18: =AVERAGE(G9,H9) -> 90798.346 | I18: =AVERAGE(H9,I9) -> 91479.9 | J18: =AVERAGE(I9,J9) -> 92624.537 | K18: =AVERAGE(J9,K9) -> 94247.19 | L18: =AVERAGE(D18:G18) -> 90743.719 | M18: =AVERAGE(H18:K18) -> 92287.493
B19: Avg – Corporate & wholesale | D19: =AVERAGE(C10,D10) -> 383889.27 | E19: =AVERAGE(D10,E10) -> 393486.5 | F19: =AVERAGE(E10,F10) -> 402327.8 | G19: =AVERAGE(F10,G10) -> 410374.35 | H19: =AVERAGE(G10,H10) -> 418581.84 | I19: =AVERAGE(H10,I10) -> 426953.48 | J19: =AVERAGE(I10,J10) -> 435492.55 | K19: =AVERAGE(J10,K10) -> 444202.4 | L19: =AVERAGE(D19:G19) -> 397519.48 | M19: =AVERAGE(H19:K19) -> 431307.57
B20: Average net advances | D20: =SUM(D15:D19) -> 1567132.2 | E20: =SUM(E15:E19) -> 1589936.7 | F20: =SUM(F15:F19) -> 1605981.5 | G20: =SUM(G15:G19) -> 1620274.9 | H20: =SUM(H15:H19) -> 1638917.5 | I20: =SUM(I15:I19) -> 1663302.5 | J20: =SUM(J15:J19) -> 1693545 | K20: =SUM(K15:K19) -> 1729420.7 | L20: =AVERAGE(D20:G20) -> 1595831.3 | M20: =AVERAGE(H20:K20) -> 1681296.4
B21: LENDING YIELDS (ANNUAL)
B22: Yield – Secured retail (mortgages, auto, gold) | C22: 0.087 | D22: =$C22+Market!$C$19*Market!D8+Decisions!D13/10000 -> 0.087 | E22: =$C22+Market!$C$19*Market!E8+Decisions!E13/10000 -> 0.0845 | F22: =$C22+Market!$C$19*Market!F8+Decisions!F13/10000 -> 0.083 | G22: =$C22+Market!$C$19*Market!G8+Decisions!G13/10000 -> 0.0815 | H22: =$C22+Market!$C$19*Market!H8+Decisions!H13/10000 -> 0.0815 | I22: =$C22+Market!$C$19*Market!I8+Decisions!I13/10000 -> 0.0815 | J22: =$C22+Market!$C$19*Market!J8+Decisions!J13/10000 -> 0.0825 | K22: =$C22+Market!$C$19*Market!K8+Decisions!K13/10000 -> 0.084 | L22: =AVERAGE(D22:G22) -> 0.084 | M22: =AVERAGE(H22:K22) -> 0.082375 | N22: Base yield 8.7% (E); floats with repo; + pricing decision
B23: Yield – Unsecured retail (personal loans, cards) | C23: 0.147 | D23: =$C23+Decisions!D12/10000 -> 0.147 | E23: =$C23+Decisions!E12/10000 -> 0.1495 | F23: =$C23+Decisions!F12/10000 -> 0.152 | G23: =$C23+Decisions!G12/10000 -> 0.152 | H23: =$C23+Decisions!H12/10000 -> 0.152 | I23: =$C23+Decisions!I12/10000 -> 0.1495 | J23: =$C23+Decisions!J12/10000 -> 0.147 | K23: =$C23+Decisions!K12/10000 -> 0.147 | L23: =AVERAGE(D23:G23) -> 0.150125 | M23: =AVERAGE(H23:K23) -> 0.148875 | N23: Base yield 14.7% (E); fixed-rate; + pricing decision
B24: Yield – Business banking & SME | C24: 0.097 | D24: =$C24+Market!$C$19*Market!D8+Decisions!D12/10000 -> 0.097 | E24: =$C24+Market!$C$19*Market!E8+Decisions!E12/10000 -> 0.098 | F24: =$C24+Market!$C$19*Market!F8+Decisions!F12/10000 -> 0.099 | G24: =$C24+Market!$C$19*Market!G8+Decisions!G12/10000 -> 0.0975 | H24: =$C24+Market!$C$19*Market!H8+Decisions!H12/10000 -> 0.0975 | I24: =$C24+Market!$C$19*Market!I8+Decisions!I12/10000 -> 0.095 | J24: =$C24+Market!$C$19*Market!J8+Decisions!J12/10000 -> 0.0925 | K24: =$C24+Market!$C$19*Market!K8+Decisions!K12/10000 -> 0.094 | L24: =AVERAGE(D24:G24) -> 0.097875 | M24: =AVERAGE(H24:K24) -> 0.09475 | N24: Base yield 9.7% (E); floats with repo; + pricing decision
B25: Yield – Rural & agri | C25: 0.102 | D25: =$C25+Market!$C$19*Market!D8 -> 0.102 | E25: =$C25+Market!$C$19*Market!E8 -> 0.1005 | F25: =$C25+Market!$C$19*Market!F8 -> 0.099 | G25: =$C25+Market!$C$19*Market!G8 -> 0.0975 | H25: =$C25+Market!$C$19*Market!H8 -> 0.0975 | I25: =$C25+Market!$C$19*Market!I8 -> 0.0975 | J25: =$C25+Market!$C$19*Market!J8 -> 0.0975 | K25: =$C25+Market!$C$19*Market!K8 -> 0.099 | L25: =AVERAGE(D25:G25) -> 0.09975 | M25: =AVERAGE(H25:K25) -> 0.097875 | N25: Base yield 10.2% (E); floats with repo
B26: Yield – Corporate & wholesale | C26: 0.077 | D26: =$C26+Market!$C$19*Market!D8 -> 0.077 | E26: =$C26+Market!$C$19*Market!E8 -> 0.0755 | F26: =$C26+Market!$C$19*Market!F8 -> 0.074 | G26: =$C26+Market!$C$19*Market!G8 -> 0.0725 | H26: =$C26+Market!$C$19*Market!H8 -> 0.0725 | I26: =$C26+Market!$C$19*Market!I8 -> 0.0725 | J26: =$C26+Market!$C$19*Market!J8 -> 0.0725 | K26: =$C26+Market!$C$19*Market!K8 -> 0.074 | L26: =AVERAGE(D26:G26) -> 0.07475 | M26: =AVERAGE(H26:K26) -> 0.072875 | N26: Base yield 7.7% (E); floats with repo
B27: Blended yield on advances | C27: =SUMPRODUCT(C22:C26,C6:C10)/C11 -> 0.09457 | D27: =D28*4/D20 -> 0.09446366 | E27: =E28*4/E20 -> 0.093265141 | F27: =F28*4/F20 -> 0.092368761 | G27: =G28*4/G20 -> 0.090725233 | H27: =H28*4/H20 -> 0.090488464 | I27: =I28*4/I20 -> 0.089585291 | J27: =J28*4/J20 -> 0.089150061 | K27: =K28*4/K20 -> 0.090448065 | L27: =L28/L20 -> 0.092689159 | M27: =M28/M20 -> 0.08991766
B28: INTEREST INCOME ON ADVANCES | D28: =(D15*D22+D16*D23+D17*D24+D18*D25+D19*D26)/4 -> 37009.26 | E28: =(E15*E22+E16*E23+E17*E24+E18*E25+E19*E26)/4 -> 37071.419 | F28: =(F15*F22+F16*F23+F17*F24+F18*F25+F19*F26)/4 -> 37085.63 | G28: =(G15*G22+G16*G23+G17*G24+G18*G25+G19*G26)/4 -> 36749.955 | H28: =(H15*H22+H16*H23+H17*H24+H18*H25+H19*H26)/4 -> 37075.782 | I28: =(I15*I22+I16*I23+I17*I24+I18*I25+I19*I26)/4 -> 37251.859 | J28: =(J15*J22+J16*J23+J17*J24+J18*J25+J19*J26)/4 -> 37744.909 | K28: =(K15*K22+K16*K23+K17*K24+K18*K25+K19*K26)/4 -> 39105.688 | L28: =SUM(D28:G28) -> 147916.26 | M28: =SUM(H28:K28) -> 151178.24

Sheet NPA_Provisions
A1: ASSET QUALITY, SLIPPAGES & PROVISIONS
A2: Gross NPA roll-forward: opening + fresh slippages − recoveries/upgrades − write-offs. Provisions follow the coverage target and contingency decisions.
B4: Particulars | C4: Mar-26 / FY26 (A) | D4: Y1 Q1 | E4: Y1 Q2 | F4: Y1 Q3 | G4: Y1 Q4 | H4: Y2 Q1 | I4: Y2 Q2 | J4: Y2 Q3 | K4: Y2 Q4 | L4: Sim Year 1 | M4: Sim Year 2 | N4: Basis / note
B5: FRESH SLIPPAGES BY SEGMENT
B6: Slippages – Secured retail (mortgages, auto, gold) | C6: 0.01 | D6: =Loan_Book!C6*$C6/4*Market!D10*(1-Decisions!D19) -> 1984.0106 | E6: =Loan_Book!D6*$C6/4*Market!E10*(1-Decisions!E19) -> 2738.8296 | F6: =Loan_Book!E6*$C6/4*Market!F10*(1-Decisions!F19) -> 3423.2023 | G6: =Loan_Book!F6*$C6/4*Market!G10*(1-Decisions!G19) -> 4009.0966 | H6: =Loan_Book!G6*$C6/4*Market!H10*(1-Decisions!H19) -> 3662.3097 | I6: =Loan_Book!H6*$C6/4*Market!I10*(1-Decisions!I19) -> 3145.0352 | J6: =Loan_Book!I6*$C6/4*Market!J10*(1-Decisions!J19) -> 2535.1973 | K6: =Loan_Book!J6*$C6/4*Market!K10*(1-Decisions!K19) -> 2183.292 | L6: =SUM(D6:G6) -> 12155.139 | M6: =SUM(H6:K6) -> 11525.834 | N6: Col C = normal annual slippage rate 1.0% (E)
B7: Slippages – Unsecured retail (personal loans, cards) | C7: 0.04 | D7: =Loan_Book!C7*$C7/4*Market!D10*(1-Decisions!D19) -> 2480.0132 | E7: =Loan_Book!D7*$C7/4*Market!E10*(1-Decisions!E19) -> 3322.8448 | F7: =Loan_Book!E7*$C7/4*Market!F10*(1-Decisions!F19) -> 3977.7221 | G7: =Loan_Book!F7*$C7/4*Market!G10*(1-Decisions!G19) -> 4451.989 | H7: =Loan_Book!G7*$C7/4*Market!H10*(1-Decisions!H19) -> 3926.6543 | I7: =Loan_Book!H7*$C7/4*Market!I10*(1-Decisions!I19) -> 3279.2953 | J7: =Loan_Book!I7*$C7/4*Market!J10*(1-Decisions!J19) -> 2591.5918 | K7: =Loan_Book!J7*$C7/4*Market!K10*(1-Decisions!K19) -> 2203.4967 | L7: =SUM(D7:G7) -> 14232.569 | M7: =SUM(H7:K7) -> 12001.038 | N7: Col C = normal annual slippage rate 4.0% (E)
B8: Slippages – Business banking & SME | C8: 0.02 | D8: =Loan_Book!C8*$C8/4*Market!D10*(1-Decisions!D19) -> 2004.6774 | E8: =Loan_Book!D8*$C8/4*Market!E10*(1-Decisions!E19) -> 2767.3591 | F8: =Loan_Book!E8*$C8/4*Market!F10*(1-Decisions!F19) -> 3431.6791 | G8: =Loan_Book!F8*$C8/4*Market!G10*(1-Decisions!G19) -> 3979.4278 | H8: =Loan_Book!G8*$C8/4*Market!H10*(1-Decisions!H19) -> 3599.3925 | I8: =Loan_Book!H8*$C8/4*Market!I10*(1-Decisions!I19) -> 3066.7137 | J8: =Loan_Book!I8*$C8/4*Market!J10*(1-Decisions!J19) -> 2459.9448 | K8: =Loan_Book!J8*$C8/4*Market!K10*(1-Decisions!K19) -> 2112.2726 | L8: =SUM(D8:G8) -> 12183.143 | M8: =SUM(H8:K8) -> 11238.324 | N8: Col C = normal annual slippage rate 2.0% (E)
B9: Slippages – Rural & agri | C9: 0.025 | D9: =Loan_Book!C9*$C9/4*Market!D10*(1-Decisions!D19) -> 749.17066 | E9: =Loan_Book!D9*$C9/4*Market!E10*(1-Decisions!E19) -> 1024.0543 | F9: =Loan_Book!E9*$C9/4*Market!F10*(1-Decisions!F19) -> 1257.3112 | G9: =Loan_Book!F9*$C9/4*Market!G10*(1-Decisions!G19) -> 1443.4899 | H9: =Loan_Book!G9*$C9/4*Market!H10*(1-Decisions!H19) -> 1299.1409 | I9: =Loan_Book!H9*$C9/4*Market!I10*(1-Decisions!I19) -> 1101.3998 | J9: =Loan_Book!I9*$C9/4*Market!J10*(1-Decisions!J19) -> 879.12867 | K9: =Loan_Book!J9*$C9/4*Market!K10*(1-Decisions!K19) -> 751.1781 | L9: =SUM(D9:G9) -> 4474.0261 | M9: =SUM(H9:K9) -> 4030.8475 | N9: Col C = normal annual slippage rate 2.5% (E)
B10: Slippages – Corporate & wholesale | C10: 0.004 | D10: =Loan_Book!C10*$C10/4*Market!D10*(1-Decisions!D19) -> 504.26936 | E10: =Loan_Book!D10*$C10/4*Market!E10*(1-Decisions!E19) -> 699.53155 | F10: =Loan_Book!E10*$C10/4*Market!F10*(1-Decisions!F19) -> 880.34103 | G10: =Loan_Book!F10*$C10/4*Market!G10*(1-Decisions!G19) -> 1036.0937 | H10: =Loan_Book!G10*$C10/4*Market!H10*(1-Decisions!H19) -> 951.13399 | I10: =Loan_Book!H10*$C10/4*Market!I10*(1-Decisions!I19) -> 818.39796 | J10: =Loan_Book!I10*$C10/4*Market!J10*(1-Decisions!J19) -> 659.70653 | K10: =Loan_Book!J10*$C10/4*Market!K10*(1-Decisions!K19) -> 566.46801 | L10: =SUM(D10:G10) -> 3120.2356 | M10: =SUM(H10:K10) -> 2995.7065 | N10: Col C = normal annual slippage rate 0.4% (E)
B11: TOTAL FRESH SLIPPAGES | D11: =SUM(D6:D10) -> 7722.1412 | E11: =SUM(E6:E10) -> 10552.619 | F11: =SUM(F6:F10) -> 12970.256 | G11: =SUM(G6:G10) -> 14920.097 | H11: =SUM(H6:H10) -> 13438.631 | I11: =SUM(I6:I10) -> 11410.842 | J11: =SUM(J6:J10) -> 9125.5691 | K11: =SUM(K6:K10) -> 7816.7074 | L11: =SUM(D11:G11) -> 46165.113 | M11: =SUM(H11:K11) -> 41791.75
B12: Slippage ratio (annualised, % of opening advances) | D12: =D11*4/Loan_Book!C11 -> 0.01987818 | E12: =E11*4/Loan_Book!D11 -> 0.026709215 | F12: =F11*4/Loan_Book!E11 -> 0.032435732 | G12: =G11*4/Loan_Book!F11 -> 0.037011992 | H12: =H11*4/Loan_Book!G11 -> 0.033016945 | I12: =I11*4/Loan_Book!H11 -> 0.027666906 | J12: =J11*4/Loan_Book!I11 -> 0.021768245 | K12: =K11*4/Loan_Book!J11 -> 0.018282226 | L12: =L11/Loan_Book!C11 -> 0.029709326 | M12: =M11/Loan_Book!G11 -> 0.025669204
B13: GROSS NPA ROLL-FORWARD
B14: Opening gross NPA | D14: =C18 -> 21987.837 | E14: =D18 -> 24938.837 | F14: =E18 -> 30380.242 | G14: =F18 -> 37538.757 | H14: =G18 -> 45556.228 | I14: =H18 -> 50327.787 | J14: =I18 -> 51483.839 | K14: =J18 -> 49437.93 | L14: =D14 -> 21987.837 | M14: =H14 -> 45556.228
B15: + Fresh slippages | D15: =D11 -> 7722.1412 | E15: =E11 -> 10552.619 | F15: =F11 -> 12970.256 | G15: =G11 -> 14920.097 | H15: =H11 -> 13438.631 | I15: =I11 -> 11410.842 | J15: =J11 -> 9125.5691 | K15: =K11 -> 7816.7074 | L15: =SUM(D15:G15) -> 46165.113 | M15: =SUM(H15:K15) -> 41791.75
B16: − Recoveries & upgrades | C16: 0.14 | D16: =-D14*$C16*Market!D11*(1+Decisions!D20/100*Market!$C$26) -> -3012.1138 | E16: =-E14*$C16*Market!E11*(1+Decisions!E20/100*Market!$C$26) -> -3116.1077 | F16: =-F14*$C16*Market!F11*(1+Decisions!F20/100*Market!$C$26) -> -3381.3209 | G16: =-G14*$C16*Market!G11*(1+Decisions!G20/100*Market!$C$26) -> -3899.5261 | H16: =-H14*$C16*Market!H11*(1+Decisions!H20/100*Market!$C$26) -> -5022.5741 | I16: =-I14*$C16*Market!I11*(1+Decisions!I20/100*Market!$C$26) -> -6228.5669 | J16: =-J14*$C16*Market!J11*(1+Decisions!J20/100*Market!$C$26) -> -7052.7711 | K16: =-K14*$C16*Market!K11*(1+Decisions!K20/100*Market!$C$26) -> -7059.7364 | L16: =SUM(D16:G16) -> -13409.069 | M16: =SUM(H16:K16) -> -25363.648 | N16: Col C = normal 14% of opening GNPA per quarter (A: Q4 FY26 ₹3,068 cr on ~₹22,000 cr)
B17: − Write-offs | C17: 0.08 | D17: =-D14*$C17 -> -1759.027 | E17: =-E14*$C17 -> -1995.107 | F17: =-F14*$C17 -> -2430.4194 | G17: =-G14*$C17 -> -3003.1006 | H17: =-H14*$C17 -> -3644.4982 | I17: =-I14*$C17 -> -4026.2229 | J17: =-J14*$C17 -> -4118.7071 | K17: =-K14*$C17 -> -3955.0344 | L17: =SUM(D17:G17) -> -9187.6539 | M17: =SUM(H17:K17) -> -15744.463 | N17: Col C = 8% of opening GNPA per quarter (A: Q4 FY26 ₹1,768 cr)
B18: CLOSING GROSS NPA | C18: =Loan_Book!C11*Baseline!D19/(1-Baseline!D19*C20) -> 21987.837 | D18: =SUM(D14:D17) -> 24938.837 | E18: =SUM(E14:E17) -> 30380.242 | F18: =SUM(F14:F17) -> 37538.757 | G18: =SUM(G14:G17) -> 45556.228 | H18: =SUM(H14:H17) -> 50327.787 | I18: =SUM(I14:I17) -> 51483.839 | J18: =SUM(J14:J17) -> 49437.93 | K18: =SUM(K14:K17) -> 46239.866 | L18: =G18 -> 45556.228 | M18: =K18 -> 46239.866 | N18: Opening = net advances × 1.40% ÷ (1 − 1.40% × PCR) (D); ties exactly to reported GNPA ratio
B19: PROVISION STOCK & RATIOS
B20: Target PCR | C20: =Decisions!C21 -> 0.758 | D20: =Decisions!D21 -> 0.75 | E20: =Decisions!E21 -> 0.76 | F20: =Decisions!F21 -> 0.77 | G20: =Decisions!G21 -> 0.78 | H20: =Decisions!H21 -> 0.78 | I20: =Decisions!I21 -> 0.78 | J20: =Decisions!J21 -> 0.78 | K20: =Decisions!K21 -> 0.78 | L20: =G20 -> 0.78 | M20: =K20 -> 0.78
B21: Specific provision stock | C21: =C18*C20 -> 16666.78 | D21: =D18*D20 -> 18704.128 | E21: =E18*E20 -> 23088.984 | F21: =F18*F20 -> 28904.843 | G21: =G18*G20 -> 35533.858 | H21: =H18*H20 -> 39255.674 | I21: =I18*I20 -> 40157.394 | J21: =J18*J20 -> 38561.585 | K21: =K18*K20 -> 36067.096 | L21: =G21 -> 35533.858 | M21: =K21 -> 36067.096
B22: Net NPA | C22: =C18-C21 -> 5321.0565 | D22: =D18-D21 -> 6234.7093 | E22: =E18-E21 -> 7291.2581 | F22: =F18-F21 -> 8633.9142 | G22: =G18-G21 -> 10022.37 | H22: =H18-H21 -> 11072.113 | I22: =I18-I21 -> 11326.445 | J22: =J18-J21 -> 10876.345 | K22: =K18-K21 -> 10172.771 | L22: =G22 -> 10022.37 | M22: =K22 -> 10172.771
B23: Gross advances (net + specific provisions) | C23: =Loan_Book!C11+C21 -> 1570559.8 | D23: =Loan_Book!D11+D21 -> 1599075.5 | E23: =Loan_Book!E11+E21 -> 1622591.1 | F23: =Loan_Book!F11+F21 -> 1641365.7 | G23: =Loan_Book!G11+G21 -> 1663622.9 | H23: =Loan_Book!H11+H21 -> 1689001.7 | I23: =Loan_Book!I11+I21 -> 1717016.3 | J23: =Loan_Book!J11+J21 -> 1748792.6 | K23: =Loan_Book!K11+K21 -> 1784677.5 | L23: =G23 -> 1663622.9 | M23: =K23 -> 1784677.5
B24: GROSS NPA RATIO | C24: =C18/C23 -> 0.014 | D24: =D18/D23 -> 0.015595785 | E24: =E18/E23 -> 0.018723289 | F24: =F18/F23 -> 0.022870441 | G24: =G18/G23 -> 0.027383747 | H24: =H18/H23 -> 0.029797357 | I24: =I18/I23 -> 0.029984478 | J24: =J18/J23 -> 0.028269751 | K24: =K18/K23 -> 0.025909369 | L24: =G24 -> 0.027383747 | M24: =K24 -> 0.025909369
B25: NET NPA RATIO | C25: =C22/Loan_Book!C11 -> 0.0034243391 | D25: =D22/Loan_Book!D11 -> 0.0039450914 | E25: =E22/Loan_Book!E11 -> 0.0045584547 | F25: =F22/Loan_Book!F11 -> 0.0053544954 | G25: =G22/Loan_Book!G11 -> 0.0061559103 | H25: =H22/Loan_Book!H11 -> 0.0067114047 | I25: =I22/Loan_Book!I11 -> 0.0067545602 | J25: =J22/Loan_Book!J11 -> 0.0063595764 | K25: =K22/Loan_Book!K11 -> 0.0058176314 | L25: =G25 -> 0.0061559103 | M25: =K25 -> 0.0058176314
B26: P&L PROVISION CHARGE
B27: Specific provisions (Δ stock + write-offs) | D27: =D21-C21-D17 -> 3796.3746 | E27: =E21-D21-E17 -> 6379.963 | F27: =F21-E21-F17 -> 8246.2786 | G27: =G21-F21-G17 -> 9632.115 | H27: =H21-G21-H17 -> 7366.3143 | I27: =I21-H21-I17 -> 4927.9436 | J27: =J21-I21-J17 -> 2522.898 | K27: =K21-J21-K17 -> 1460.545 | L27: =SUM(D27:G27) -> 28054.731 | M27: =SUM(H27:K27) -> 16277.701
B28: Standard-asset provisions (0.4% of net loan growth) | D28: =MAX(0,Loan_Book!D11-Loan_Book!C11)*0.004 -> 105.91335 | E28: =MAX(0,Loan_Book!E11-Loan_Book!D11)*0.004 -> 76.523263 | F28: =MAX(0,Loan_Book!F11-Loan_Book!E11)*0.004 -> 51.834748 | G28: =MAX(0,Loan_Book!G11-Loan_Book!F11)*0.004 -> 62.512788 | H28: =MAX(0,Loan_Book!H11-Loan_Book!G11)*0.004 -> 86.627892 | I28: =MAX(0,Loan_Book!I11-Loan_Book!H11)*0.004 -> 108.4517 | J28: =MAX(0,Loan_Book!J11-Loan_Book!I11)*0.004 -> 133.48817 | K28: =MAX(0,Loan_Book!K11-Loan_Book!J11)*0.004 -> 153.51757 | L28: =SUM(D28:G28) -> 296.78415 | M28: =SUM(H28:K28) -> 482.08533
B29: Contingency provision add / (release) | D29: =Decisions!D22 -> 1000 | E29: =Decisions!E22 -> 500 | F29: =Decisions!F22 -> -1500 | G29: =Decisions!G22 -> -3000 | H29: =Decisions!H22 -> -2000 | I29: =Decisions!I22 -> 0 | J29: =Decisions!J22 -> 500 | K29: =Decisions!K22 -> 1000 | L29: =SUM(D29:G29) -> -3000 | M29: =SUM(H29:K29) -> -500
B30: TOTAL PROVISIONS | D30: =SUM(D27:D29) -> 4902.2879 | E30: =SUM(E27:E29) -> 6956.4862 | F30: =SUM(F27:F29) -> 6798.1134 | G30: =SUM(G27:G29) -> 6694.6277 | H30: =SUM(H27:H29) -> 5452.9422 | I30: =SUM(I27:I29) -> 5036.3953 | J30: =SUM(J27:J29) -> 3156.3862 | K30: =SUM(K27:K29) -> 2614.0626 | L30: =SUM(D30:G30) -> 25351.515 | M30: =SUM(H30:K30) -> 16259.786
B31: Contingency provision stock | C31: =Baseline!D26 -> 13100 | D31: =C31+D29 -> 14100 | E31: =D31+E29 -> 14600 | F31: =E31+F29 -> 13100 | G31: =F31+G29 -> 10100 | H31: =G31+H29 -> 8100 | I31: =H31+I29 -> 8100 | J31: =I31+J29 -> 8600 | K31: =J31+K29 -> 9600 | L31: =G31 -> 10100 | M31: =K31 -> 9600
B32: Credit cost (annualised, % of avg advances) | D32: =D30*4/Loan_Book!D20 -> 0.012512762 | E32: =E30*4/Loan_Book!E20 -> 0.017501291 | F32: =F30*4/Loan_Book!F20 -> 0.016931984 | G32: =G30*4/Loan_Book!G20 -> 0.01652714 | H32: =H30*4/Loan_Book!H20 -> 0.013308643 | I32: =I30*4/Loan_Book!I20 -> 0.012111797 | J32: =J30*4/Loan_Book!J20 -> 0.0074550986 | K32: =K30*4/Loan_Book!K20 -> 0.0060460999 | L32: =L30/Loan_Book!L20 -> 0.015886087 | M32: =M30/Loan_Book!M20 -> 0.0096709814
B33: EXPECTED LOSS (FOR RAROC)
B34: Expected loss – Secured retail (mortgages, auto, gold) | C34: 0.25 | D34: =Loan_Book!D15*NPA_Provisions!$C6*Market!D10*(1-Decisions!D19)*$C34/4 -> 500.96267 | E34: =Loan_Book!E15*NPA_Provisions!$C6*Market!E10*(1-Decisions!E19)*$C34/4 -> 690.86978 | F34: =Loan_Book!F15*NPA_Provisions!$C6*Market!F10*(1-Decisions!F19)*$C34/4 -> 862.21908 | G34: =Loan_Book!G15*NPA_Provisions!$C6*Market!G10*(1-Decisions!G19)*$C34/4 -> 1009.7912 | H34: =Loan_Book!H15*NPA_Provisions!$C6*Market!H10*(1-Decisions!H19)*$C34/4 -> 923.81762 | I34: =Loan_Book!I15*NPA_Provisions!$C6*Market!I10*(1-Decisions!I19)*$C34/4 -> 794.12138 | J34: =Loan_Book!J15*NPA_Provisions!$C6*Market!J10*(1-Decisions!J19)*$C34/4 -> 641.08801 | K34: =Loan_Book!K15*NPA_Provisions!$C6*Market!K10*(1-Decisions!K19)*$C34/4 -> 552.64579 | L34: =SUM(D34:G34) -> 3063.8427 | M34: =SUM(H34:K34) -> 2911.6728 | N34: EL = avg balance × PD × LGD; col C = LGD 25% (E)
B35: Expected loss – Unsecured retail (personal loans, cards) | C35: 0.65 | D35: =Loan_Book!D16*NPA_Provisions!$C7*Market!D10*(1-Decisions!D19)*$C35/4 -> 1603.9486 | E35: =Loan_Book!E16*NPA_Provisions!$C7*Market!E10*(1-Decisions!E19)*$C35/4 -> 2132.851 | F35: =Loan_Book!F16*NPA_Provisions!$C7*Market!F10*(1-Decisions!F19)*$C35/4 -> 2546.7366 | G35: =Loan_Book!G16*NPA_Provisions!$C7*Market!G10*(1-Decisions!G19)*$C35/4 -> 2864.8549 | H35: =Loan_Book!H16*NPA_Provisions!$C7*Market!H10*(1-Decisions!H19)*$C35/4 -> 2539.5637 | I35: =Loan_Book!I16*NPA_Provisions!$C7*Market!I10*(1-Decisions!I19)*$C35/4 -> 2131.5419 | J35: =Loan_Book!J16*NPA_Provisions!$C7*Market!J10*(1-Decisions!J19)*$C35/4 -> 1692.9574 | K35: =Loan_Book!K16*NPA_Provisions!$C7*Market!K10*(1-Decisions!K19)*$C35/4 -> 1443.0149 | L35: =SUM(D35:G35) -> 9148.3911 | M35: =SUM(H35:K35) -> 7807.0779 | N35: EL = avg balance × PD × LGD; col C = LGD 65% (E)
B36: Expected loss – Business banking & SME | C36: 0.4 | D36: =Loan_Book!D17*NPA_Provisions!$C8*Market!D10*(1-Decisions!D19)*$C36/4 -> 809.88965 | E36: =Loan_Book!E17*NPA_Provisions!$C8*Market!E10*(1-Decisions!E19)*$C36/4 -> 1112.4784 | F36: =Loan_Book!F17*NPA_Provisions!$C8*Market!F10*(1-Decisions!F19)*$C36/4 -> 1376.1033 | G36: =Loan_Book!G17*NPA_Provisions!$C8*Market!G10*(1-Decisions!G19)*$C36/4 -> 1595.7506 | H36: =Loan_Book!H17*NPA_Provisions!$C8*Market!H10*(1-Decisions!H19)*$C36/4 -> 1446.9558 | I36: =Loan_Book!I17*NPA_Provisions!$C8*Market!I10*(1-Decisions!I19)*$C36/4 -> 1235.8856 | J36: =Loan_Book!J17*NPA_Provisions!$C8*Market!J10*(1-Decisions!J19)*$C36/4 -> 993.8177 | K36: =Loan_Book!K17*NPA_Provisions!$C8*Market!K10*(1-Decisions!K19)*$C36/4 -> 855.4704 | L36: =SUM(D36:G36) -> 4894.2219 | M36: =SUM(H36:K36) -> 4532.1295 | N36: EL = avg balance × PD × LGD; col C = LGD 40% (E)
B37: Expected loss – Rural & agri | C37: 0.45 | D37: =Loan_Book!D18*NPA_Provisions!$C9*Market!D10*(1-Decisions!D19)*$C37/4 -> 338.81243 | E37: =Loan_Book!E18*NPA_Provisions!$C9*Market!E10*(1-Decisions!E19)*$C37/4 -> 460.82445 | F37: =Loan_Book!F18*NPA_Provisions!$C9*Market!F10*(1-Decisions!F19)*$C37/4 -> 564.37554 | G37: =Loan_Book!G18*NPA_Provisions!$C9*Market!G10*(1-Decisions!G19)*$C37/4 -> 649.57046 | H37: =Loan_Book!H18*NPA_Provisions!$C9*Market!H10*(1-Decisions!H19)*$C37/4 -> 586.07495 | I37: =Loan_Book!I18*NPA_Provisions!$C9*Market!I10*(1-Decisions!I19)*$C37/4 -> 498.10806 | J37: =Loan_Book!J18*NPA_Provisions!$C9*Market!J10*(1-Decisions!J19)*$C37/4 -> 398.57496 | K37: =Loan_Book!K18*NPA_Provisions!$C9*Market!K10*(1-Decisions!K19)*$C37/4 -> 341.41045 | L37: =SUM(D37:G37) -> 2013.5829 | M37: =SUM(H37:K37) -> 1824.1684 | N37: EL = avg balance × PD × LGD; col C = LGD 45% (E)
B38: Expected loss – Corporate & wholesale | C38: 0.45 | D38: =Loan_Book!D19*NPA_Provisions!$C10*Market!D10*(1-Decisions!D19)*$C38/4 -> 229.75773 | E38: =Loan_Book!E19*NPA_Provisions!$C10*Market!E10*(1-Decisions!E19)*$C38/4 -> 318.72406 | F38: =Loan_Book!F19*NPA_Provisions!$C10*Market!F10*(1-Decisions!F19)*$C38/4 -> 400.115 | G38: =Loan_Book!G19*NPA_Provisions!$C10*Market!G10*(1-Decisions!G19)*$C38/4 -> 470.90457 | H38: =Loan_Book!H19*NPA_Provisions!$C10*Market!H10*(1-Decisions!H19)*$C38/4 -> 432.2904 | I38: =Loan_Book!I19*NPA_Provisions!$C10*Market!I10*(1-Decisions!I19)*$C38/4 -> 371.96187 | J38: =Loan_Book!J19*NPA_Provisions!$C10*Market!J10*(1-Decisions!J19)*$C38/4 -> 299.83662 | K38: =Loan_Book!K19*NPA_Provisions!$C10*Market!K10*(1-Decisions!K19)*$C38/4 -> 257.45971 | L38: =SUM(D38:G38) -> 1419.5014 | M38: =SUM(H38:K38) -> 1361.5486 | N38: EL = avg balance × PD × LGD; col C = LGD 45% (E)
B39: TOTAL EXPECTED LOSS | D39: =SUM(D34:D38) -> 3483.371 | E39: =SUM(E34:E38) -> 4715.7477 | F39: =SUM(F34:F38) -> 5749.5495 | G39: =SUM(G34:G38) -> 6590.8717 | H39: =SUM(H34:H38) -> 5928.7024 | I39: =SUM(I34:I38) -> 5031.6189 | J39: =SUM(J34:J38) -> 4026.2746 | K39: =SUM(K34:K38) -> 3450.0013 | L39: =SUM(D39:G39) -> 20539.54 | M39: =SUM(H39:K39) -> 18436.597

Sheet Funding
A1: DEPOSITS, CASA & COST OF FUNDS
A2: Deposit growth = system growth + effect of our term-deposit premium and marketing. CASA ratio drifts with the market and our salary/current-account campaigns.
B4: Particulars | C4: Mar-26 / FY26 (A) | D4: Y1 Q1 | E4: Y1 Q2 | F4: Y1 Q3 | G4: Y1 Q4 | H4: Y2 Q1 | I4: Y2 Q2 | J4: Y2 Q3 | K4: Y2 Q4 | L4: Sim Year 1 | M4: Sim Year 2 | N4: Basis / note
B5: Deposit growth (quarterly) | D5: =Market!D12+Decisions!D14/10*Market!$C$23+Decisions!D16/100*Market!$C$24 -> 0.0262 | E5: =Market!E12+Decisions!E14/10*Market!$C$23+Decisions!E16/100*Market!$C$24 -> 0.0246 | F5: =Market!F12+Decisions!F14/10*Market!$C$23+Decisions!F16/100*Market!$C$24 -> 0.0232 | G5: =Market!G12+Decisions!G14/10*Market!$C$23+Decisions!G16/100*Market!$C$24 -> 0.023 | H5: =Market!H12+Decisions!H14/10*Market!$C$23+Decisions!H16/100*Market!$C$24 -> 0.0234 | I5: =Market!I12+Decisions!I14/10*Market!$C$23+Decisions!I16/100*Market!$C$24 -> 0.025 | J5: =Market!J12+Decisions!J14/10*Market!$C$23+Decisions!J16/100*Market!$C$24 -> 0.0266 | K5: =Market!K12+Decisions!K14/10*Market!$C$23+Decisions!K16/100*Market!$C$24 -> 0.0276 | L5: =L6/C6-1 -> 0.10058231 | M5: =M6/L6-1 -> 0.10661011
B6: TOTAL DEPOSITS | C6: =Baseline!D16 -> 1794625 | D6: =C6*(1+D5) -> 1841644.2 | E6: =D6*(1+E5) -> 1886948.6 | F6: =E6*(1+F5) -> 1930725.8 | G6: =F6*(1+G5) -> 1975132.5 | H6: =G6*(1+H5) -> 2021350.6 | I6: =H6*(1+I5) -> 2071884.4 | J6: =I6*(1+J5) -> 2126996.5 | K6: =J6*(1+K5) -> 2185701.6 | L6: =G6 -> 1975132.5 | M6: =K6 -> 2185701.6
B7: CASA ratio | C7: =Baseline!D25 -> 0.414 | D7: =MIN(0.45,MAX(0.3,C7+Market!D14+Decisions!D16/100*Market!$C$25)) -> 0.4115 | E7: =MIN(0.45,MAX(0.3,D7+Market!E14+Decisions!E16/100*Market!$C$25)) -> 0.40725 | F7: =MIN(0.45,MAX(0.3,E7+Market!F14+Decisions!F16/100*Market!$C$25)) -> 0.403 | G7: =MIN(0.45,MAX(0.3,F7+Market!G14+Decisions!G16/100*Market!$C$25)) -> 0.4005 | H7: =MIN(0.45,MAX(0.3,G7+Market!H14+Decisions!H16/100*Market!$C$25)) -> 0.4 | I7: =MIN(0.45,MAX(0.3,H7+Market!I14+Decisions!I16/100*Market!$C$25)) -> 0.40175 | J7: =MIN(0.45,MAX(0.3,I7+Market!J14+Decisions!J16/100*Market!$C$25)) -> 0.40575 | K7: =MIN(0.45,MAX(0.3,J7+Market!K14+Decisions!K16/100*Market!$C$25)) -> 0.41075 | L7: =G7 -> 0.4005 | M7: =K7 -> 0.41075
B8: CASA deposits | C8: =C6*C7 -> 742974.75 | D8: =D6*D7 -> 757836.58 | E8: =E6*E7 -> 768459.83 | F8: =F6*F7 -> 778082.51 | G8: =G6*G7 -> 791040.58 | H8: =H6*H7 -> 808540.25 | I8: =I6*I7 -> 832379.55 | J8: =J6*J7 -> 863028.84 | K8: =K6*K7 -> 897776.94 | L8: =G8 -> 791040.58 | M8: =K8 -> 897776.94
B9: Term deposits | C9: =C6-C8 -> 1051650.2 | D9: =D6-D8 -> 1083807.6 | E9: =E6-E8 -> 1118488.8 | F9: =F6-F8 -> 1152643.3 | G9: =G6-G8 -> 1184091.9 | H9: =H6-H8 -> 1212810.4 | I9: =I6-I8 -> 1239504.8 | J9: =J6-J8 -> 1263967.7 | K9: =K6-K8 -> 1287924.7 | L9: =G9 -> 1184091.9 | M9: =K9 -> 1287924.7
B10: Average deposits | D10: =AVERAGE(C6,D6) -> 1818134.6 | E10: =AVERAGE(D6,E6) -> 1864296.4 | F10: =AVERAGE(E6,F6) -> 1908837.2 | G10: =AVERAGE(F6,G6) -> 1952929.2 | H10: =AVERAGE(G6,H6) -> 1998241.6 | I10: =AVERAGE(H6,I6) -> 2046617.5 | J10: =AVERAGE(I6,J6) -> 2099440.5 | K10: =AVERAGE(J6,K6) -> 2156349.1 | L10: =AVERAGE(D10:G10) -> 1886049.3 | M10: =AVERAGE(H10:K10) -> 2075162.2
B11: CASA rate (annual) | C11: 0.026 | D11: =$C11+Market!$C$21*Market!D8 -> 0.026 | E11: =$C11+Market!$C$21*Market!E8 -> 0.02575 | F11: =$C11+Market!$C$21*Market!F8 -> 0.0255 | G11: =$C11+Market!$C$21*Market!G8 -> 0.02525 | H11: =$C11+Market!$C$21*Market!H8 -> 0.02525 | I11: =$C11+Market!$C$21*Market!I8 -> 0.02525 | J11: =$C11+Market!$C$21*Market!J8 -> 0.02525 | K11: =$C11+Market!$C$21*Market!K8 -> 0.0255 | L11: =AVERAGE(D11:G11) -> 0.025625 | M11: =AVERAGE(H11:K11) -> 0.0253125 | N11: E – blended savings/current account cost
B12: Term-deposit rate (annual) | C12: 0.062 | D12: =$C12+Market!$C$20*Market!D8+Decisions!D14/10000 -> 0.062 | E12: =$C12+Market!$C$20*Market!E8+Decisions!E14/10000 -> 0.061875 | F12: =$C12+Market!$C$20*Market!F8+Decisions!F14/10000 -> 0.06125 | G12: =$C12+Market!$C$20*Market!G8+Decisions!G14/10000 -> 0.060125 | H12: =$C12+Market!$C$20*Market!H8+Decisions!H14/10000 -> 0.059625 | I12: =$C12+Market!$C$20*Market!I8+Decisions!I14/10000 -> 0.059125 | J12: =$C12+Market!$C$20*Market!J8+Decisions!J14/10000 -> 0.058625 | K12: =$C12+Market!$C$20*Market!K8+Decisions!K14/10000 -> 0.05975 | L12: =AVERAGE(D12:G12) -> 0.0613125 | M12: =AVERAGE(H12:K12) -> 0.05928125 | N12: E – includes our premium decision
B13: Cost of deposits | C13: =C7*C11+(1-C7)*C12 -> 0.047096 | D13: =D7*D11+(1-D7)*D12 -> 0.047186 | E13: =E7*E11+(1-E7)*E12 -> 0.047163094 | F13: =F7*F11+(1-F7)*F12 -> 0.04684275 | G13: =G7*G11+(1-G7)*G12 -> 0.046157562 | H13: =H7*H11+(1-H7)*H12 -> 0.045875 | I13: =I7*I11+(1-I7)*I12 -> 0.045515719 | J13: =J7*J11+(1-J7)*J12 -> 0.045083094 | K13: =K7*K11+(1-K7)*K12 -> 0.045681813 | L13: =AVERAGE(D13:G13) -> 0.046837352 | M13: =AVERAGE(H13:K13) -> 0.045538906
B14: INTEREST ON DEPOSITS | D14: =D10*D13/4 -> 21447.625 | E14: =E10*E13/4 -> 21981.496 | F14: =F10*F13/4 -> 22353.796 | G14: =G10*G13/4 -> 22535.613 | H14: =H10*H13/4 -> 22917.333 | I14: =I10*I13/4 -> 23288.317 | J14: =J10*J13/4 -> 23662.318 | K14: =K10*K13/4 -> 24626.483 | L14: =SUM(D14:G14) -> 88318.53 | M14: =SUM(H14:K14) -> 94494.451
B15: Borrowings | C15: 100000 | D15: =C15 -> 100000 | E15: =D15 -> 100000 | F15: =E15 -> 100000 | G15: =F15 -> 100000 | H15: =G15 -> 100000 | I15: =H15 -> 100000 | J15: =I15 -> 100000 | K15: =J15 -> 100000 | L15: =G15 -> 100000 | M15: =K15 -> 100000 | N15: E – held flat; deposits fund growth
B16: Cost of borrowings | C16: 0.072 | D16: =$C16+0.8*Market!D8 -> 0.072 | E16: =$C16+0.8*Market!E8 -> 0.07 | F16: =$C16+0.8*Market!F8 -> 0.068 | G16: =$C16+0.8*Market!G8 -> 0.066 | H16: =$C16+0.8*Market!H8 -> 0.066 | I16: =$C16+0.8*Market!I8 -> 0.066 | J16: =$C16+0.8*Market!J8 -> 0.066 | K16: =$C16+0.8*Market!K8 -> 0.068 | L16: =AVERAGE(D16:G16) -> 0.069 | M16: =AVERAGE(H16:K16) -> 0.0665 | N16: E
B17: INTEREST ON BORROWINGS | D17: =AVERAGE(C15,D15)*D16/4 -> 1800 | E17: =AVERAGE(D15,E15)*E16/4 -> 1750 | F17: =AVERAGE(E15,F15)*F16/4 -> 1700 | G17: =AVERAGE(F15,G15)*G16/4 -> 1650 | H17: =AVERAGE(G15,H15)*H16/4 -> 1650 | I17: =AVERAGE(H15,I15)*I16/4 -> 1650 | J17: =AVERAGE(I15,J15)*J16/4 -> 1650 | K17: =AVERAGE(J15,K15)*K16/4 -> 1700 | L17: =SUM(D17:G17) -> 6900 | M17: =SUM(H17:K17) -> 6650
B18: Loan-to-deposit ratio | C18: =Loan_Book!C11/C6 -> 0.86585944 | D18: =Loan_Book!D11/D6 -> 0.85813066 | E18: =Loan_Book!E11/E6 -> 0.84766598 | F18: =Loan_Book!F11/F6 -> 0.83515785 | G18: =Loan_Book!G11/G6 -> 0.82429357 | H18: =Loan_Book!H11/H6 -> 0.81616024 | I18: =Loan_Book!I11/I6 -> 0.80934001 | J18: =Loan_Book!J11/J6 -> 0.80405913 | K18: =Loan_Book!K11/K6 -> 0.80002245 | L18: =G18 -> 0.82429357 | M18: =K18 -> 0.80002245

Sheet P&L
A1: PROFIT & LOSS (QUARTERLY)
A2: FY26 column = ICICI reported standalone (A). Y1–Y2 = simulation (S).
B4: Particulars | C4: Mar-26 / FY26 (A) | D4: Y1 Q1 | E4: Y1 Q2 | F4: Y1 Q3 | G4: Y1 Q4 | H4: Y2 Q1 | I4: Y2 Q2 | J4: Y2 Q3 | K4: Y2 Q4 | L4: Sim Year 1 | M4: Sim Year 2 | N4: Basis / note
B5: Interest on advances | D5: =Loan_Book!D28 -> 37009.26 | E5: =Loan_Book!E28 -> 37071.419 | F5: =Loan_Book!F28 -> 37085.63 | G5: =Loan_Book!G28 -> 36749.955 | H5: =Loan_Book!H28 -> 37075.782 | I5: =Loan_Book!I28 -> 37251.859 | J5: =Loan_Book!J28 -> 37744.909 | K5: =Loan_Book!K28 -> 39105.688 | L5: =SUM(D5:G5) -> 147916.26 | M5: =SUM(H5:K5) -> 151178.24
B6: Interest on investments & cash (on opening investments) | D6: =Balance_Sheet!C14*Balance_Sheet!D23/4+AVERAGE(Balance_Sheet!C13,Balance_Sheet!D13)*0.015/4 -> 9257.0289 | E6: =Balance_Sheet!D14*Balance_Sheet!E23/4+AVERAGE(Balance_Sheet!D13,Balance_Sheet!E13)*0.015/4 -> 9603.7772 | F6: =Balance_Sheet!E14*Balance_Sheet!F23/4+AVERAGE(Balance_Sheet!E13,Balance_Sheet!F13)*0.015/4 -> 9858.7753 | G6: =Balance_Sheet!F14*Balance_Sheet!G23/4+AVERAGE(Balance_Sheet!F13,Balance_Sheet!G13)*0.015/4 -> 10282.719 | H6: =Balance_Sheet!G14*Balance_Sheet!H23/4+AVERAGE(Balance_Sheet!G13,Balance_Sheet!H13)*0.015/4 -> 10771.841 | I6: =Balance_Sheet!H14*Balance_Sheet!I23/4+AVERAGE(Balance_Sheet!H13,Balance_Sheet!I13)*0.015/4 -> 11227.218 | J6: =Balance_Sheet!I14*Balance_Sheet!J23/4+AVERAGE(Balance_Sheet!I13,Balance_Sheet!J13)*0.015/4 -> 11590.419 | K6: =Balance_Sheet!J14*Balance_Sheet!K23/4+AVERAGE(Balance_Sheet!J13,Balance_Sheet!K13)*0.015/4 -> 12232.252 | L6: =SUM(D6:G6) -> 39002.301 | M6: =SUM(H6:K6) -> 45821.729
B7: TOTAL INTEREST EARNED | D7: =D5+D6 -> 46266.289 | E7: =E5+E6 -> 46675.196 | F7: =F5+F6 -> 46944.405 | G7: =G5+G6 -> 47032.674 | H7: =H5+H6 -> 47847.623 | I7: =I5+I6 -> 48479.077 | J7: =J5+J6 -> 49335.328 | K7: =K5+K6 -> 51337.94 | L7: =SUM(D7:G7) -> 186918.56 | M7: =SUM(H7:K7) -> 196999.97
B8: Interest expended | D8: =Funding!D14+Funding!D17 -> 23247.625 | E8: =Funding!E14+Funding!E17 -> 23731.496 | F8: =Funding!F14+Funding!F17 -> 24053.796 | G8: =Funding!G14+Funding!G17 -> 24185.613 | H8: =Funding!H14+Funding!H17 -> 24567.333 | I8: =Funding!I14+Funding!I17 -> 24938.317 | J8: =Funding!J14+Funding!J17 -> 25312.318 | K8: =Funding!K14+Funding!K17 -> 26326.483 | L8: =SUM(D8:G8) -> 95218.53 | M8: =SUM(H8:K8) -> 101144.45
B9: NET INTEREST INCOME | C9: =Baseline!D6 -> 88075 | D9: =D7-D8 -> 23018.664 | E9: =E7-E8 -> 22943.7 | F9: =F7-F8 -> 22890.609 | G9: =G7-G8 -> 22847.062 | H9: =H7-H8 -> 23280.29 | I9: =I7-I8 -> 23540.76 | J9: =J7-J8 -> 24023.011 | K9: =K7-K8 -> 25011.457 | L9: =SUM(D9:G9) -> 91700.035 | M9: =SUM(H9:K9) -> 95855.518 | N9: FY26 A ₹88,075 cr
B10: Fee & other income | C10: =Baseline!D7-1500 -> 29258 | D10: =$C10/4*Market!D15*Loan_Book!D20/Loan_Book!$C$11 -> 7007.9786 | E10: =$C10/4*Market!E15*Loan_Book!E20/Loan_Book!$C$11 -> 6735.7489 | F10: =$C10/4*Market!F15*Loan_Book!F20/Loan_Book!$C$11 -> 6501.3347 | G10: =$C10/4*Market!G15*Loan_Book!G20/Loan_Book!$C$11 -> 6406.6579 | H10: =$C10/4*Market!H15*Loan_Book!H20/Loan_Book!$C$11 -> 6711.8136 | I10: =$C10/4*Market!I15*Loan_Book!I20/Loan_Book!$C$11 -> 7203.1522 | J10: =$C10/4*Market!J15*Loan_Book!J20/Loan_Book!$C$11 -> 7652.9962 | K10: =$C10/4*Market!K15*Loan_Book!K20/Loan_Book!$C$11 -> 8140.7455 | L10: =SUM(D10:G10) -> 26651.72 | M10: =SUM(H10:K10) -> 29708.708 | N10: FY26 non-interest income less ~₹1,500 cr treasury (E); scales with fee activity and loan book
B11: Treasury gains / (losses) | C11: 1500 | D11: =Market!D16 -> 400 | E11: =Market!E16 -> 900 | F11: =Market!F16 -> 1100 | G11: =Market!G16 -> 700 | H11: =Market!H16 -> 300 | I11: =Market!I16 -> 200 | J11: =Market!J16 -> 100 | K11: =Market!K16 -> -200 | L11: =SUM(D11:G11) -> 3100 | M11: =SUM(H11:K11) -> 400
B12: TOTAL OPERATING INCOME | C12: =C9+C10+C11 -> 118833 | D12: =D9+D10+D11 -> 30426.643 | E12: =E9+E10+E11 -> 30579.448 | F12: =F9+F10+F11 -> 30491.944 | G12: =G9+G10+G11 -> 29953.72 | H12: =H9+H10+H11 -> 30292.103 | I12: =I9+I10+I11 -> 30943.912 | J12: =J9+J10+J11 -> 31776.007 | K12: =K9+K10+K11 -> 32952.202 | L12: =SUM(D12:G12) -> 121451.75 | M12: =SUM(H12:K12) -> 125964.23
B13: Core operating expenses | C13: =Baseline!D8 -> 47234 | D13: =$C13/4*(1+Decisions!D23) -> 11985.628 | E13: =D13*(1+Decisions!E23) -> 12105.484 | F13: =E13*(1+Decisions!F23) -> 12166.011 | G13: =F13*(1+Decisions!G23) -> 12226.841 | H13: =G13*(1+Decisions!H23) -> 12324.656 | I13: =H13*(1+Decisions!I23) -> 12447.903 | J13: =I13*(1+Decisions!J23) -> 12634.621 | K13: =J13*(1+Decisions!K23) -> 12862.044 | L13: =SUM(D13:G13) -> 48483.964 | M13: =SUM(H13:K13) -> 50269.224
B14: Marketing, digital & collections spend (incremental) | C14: 0 | D14: =Decisions!D16+Decisions!D17+Decisions!D20 -> 600 | E14: =Decisions!E16+Decisions!E17+Decisions!E20 -> 750 | F14: =Decisions!F16+Decisions!F17+Decisions!F20 -> 800 | G14: =Decisions!G16+Decisions!G17+Decisions!G20 -> 750 | H14: =Decisions!H16+Decisions!H17+Decisions!H20 -> 670 | I14: =Decisions!I16+Decisions!I17+Decisions!I20 -> 670 | J14: =Decisions!J16+Decisions!J17+Decisions!J20 -> 650 | K14: =Decisions!K16+Decisions!K17+Decisions!K20 -> 600 | L14: =SUM(D14:G14) -> 2900 | M14: =SUM(H14:K14) -> 2590
B15: TOTAL OPERATING EXPENSES | C15: =C13+C14 -> 47234 | D15: =D13+D14 -> 12585.628 | E15: =E13+E14 -> 12855.484 | F15: =F13+F14 -> 12966.011 | G15: =G13+G14 -> 12976.841 | H15: =H13+H14 -> 12994.656 | I15: =I13+I14 -> 13117.903 | J15: =J13+J14 -> 13284.621 | K15: =K13+K14 -> 13462.044 | L15: =SUM(D15:G15) -> 51383.964 | M15: =SUM(H15:K15) -> 52859.224
B16: PRE-PROVISION OPERATING PROFIT | C16: =C12-C15 -> 71599 | D16: =D12-D15 -> 17841.015 | E16: =E12-E15 -> 17723.965 | F16: =F12-F15 -> 17525.933 | G16: =G12-G15 -> 16976.878 | H16: =H12-H15 -> 17297.447 | I16: =I12-I15 -> 17826.01 | J16: =J12-J15 -> 18491.386 | K16: =K12-K15 -> 19490.158 | L16: =SUM(D16:G16) -> 70067.791 | M16: =SUM(H16:K16) -> 73105.001
B17: Provisions & contingencies | C17: =Baseline!D10 -> 5380 | D17: =NPA_Provisions!D30 -> 4902.2879 | E17: =NPA_Provisions!E30 -> 6956.4862 | F17: =NPA_Provisions!F30 -> 6798.1134 | G17: =NPA_Provisions!G30 -> 6694.6277 | H17: =NPA_Provisions!H30 -> 5452.9422 | I17: =NPA_Provisions!I30 -> 5036.3953 | J17: =NPA_Provisions!J30 -> 3156.3862 | K17: =NPA_Provisions!K30 -> 2614.0626 | L17: =SUM(D17:G17) -> 25351.515 | M17: =SUM(H17:K17) -> 16259.786 | N17: FY26 A ₹5,380 cr
B18: PROFIT BEFORE TAX | C18: =C16-C17 -> 66219 | D18: =D16-D17 -> 12938.727 | E18: =E16-E17 -> 10767.478 | F18: =F16-F17 -> 10727.819 | G18: =G16-G17 -> 10282.251 | H18: =H16-H17 -> 11844.505 | I18: =I16-I17 -> 12789.615 | J18: =J16-J17 -> 15335 | K18: =K16-K17 -> 16876.095 | L18: =SUM(D18:G18) -> 44716.276 | M18: =SUM(H18:K18) -> 56845.215
B19: Tax | C19: =C18-C21 -> 16072 | D19: =MAX(0,D18)*Market!$C$29 -> 3256.6777 | E19: =MAX(0,E18)*Market!$C$29 -> 2710.1743 | F19: =MAX(0,F18)*Market!$C$29 -> 2700.1921 | G19: =MAX(0,G18)*Market!$C$29 -> 2588.0425 | H19: =MAX(0,H18)*Market!$C$29 -> 2981.262 | I19: =MAX(0,I18)*Market!$C$29 -> 3219.146 | J19: =MAX(0,J18)*Market!$C$29 -> 3859.8194 | K19: =MAX(0,K18)*Market!$C$29 -> 4247.7132 | L19: =SUM(D19:G19) -> 11255.087 | M19: =SUM(H19:K19) -> 14307.941
B21: NET PROFIT (PAT) | C21: =Baseline!D13 -> 50147 | D21: =D18-D19 -> 9682.0496 | E21: =E18-E19 -> 8057.3041 | F21: =F18-F19 -> 8027.6272 | G21: =G18-G19 -> 7694.2082 | H21: =H18-H19 -> 8863.2433 | I21: =I18-I19 -> 9570.4686 | J21: =J18-J19 -> 11475.18 | K21: =K18-K19 -> 12628.382 | L21: =SUM(D21:G21) -> 33461.189 | M21: =SUM(H21:K21) -> 42537.274 | N21: FY26 A ₹50,147 cr
B22: KEY P&L RATIOS
B23: Net interest margin (annualised, on avg earning assets) | C23: =C9/((Balance_Sheet!C13+Balance_Sheet!C14+Balance_Sheet!C15)) -> 0.039699693 | D23: =D9*4/(AVERAGE(Balance_Sheet!C13,Balance_Sheet!D13)+Balance_Sheet!D24+Loan_Book!D20) -> 0.040970431 | E23: =E9*4/(AVERAGE(Balance_Sheet!D13,Balance_Sheet!E13)+Balance_Sheet!E24+Loan_Book!E20) -> 0.039923496 | F23: =F9*4/(AVERAGE(Balance_Sheet!E13,Balance_Sheet!F13)+Balance_Sheet!F24+Loan_Book!F20) -> 0.039021007 | G23: =G9*4/(AVERAGE(Balance_Sheet!F13,Balance_Sheet!G13)+Balance_Sheet!G24+Loan_Book!G20) -> 0.038140116 | H23: =H9*4/(AVERAGE(Balance_Sheet!G13,Balance_Sheet!H13)+Balance_Sheet!H24+Loan_Book!H20) -> 0.038053137 | I23: =I9*4/(AVERAGE(Balance_Sheet!H13,Balance_Sheet!I13)+Balance_Sheet!I24+Loan_Book!I20) -> 0.037663971 | J23: =J9*4/(AVERAGE(Balance_Sheet!I13,Balance_Sheet!J13)+Balance_Sheet!J24+Loan_Book!J20) -> 0.037535464 | K23: =K9*4/(AVERAGE(Balance_Sheet!J13,Balance_Sheet!K13)+Balance_Sheet!K24+Loan_Book!K20) -> 0.038045029 | L23: =L9/(AVERAGE(Balance_Sheet!C13,Balance_Sheet!G13)+Balance_Sheet!L24+Loan_Book!L20) -> 0.039490263 | M23: =M9/(AVERAGE(Balance_Sheet!G13,Balance_Sheet!K13)+Balance_Sheet!M24+Loan_Book!M20) -> 0.037818436
B24: Cost-to-income ratio | C24: =C15/C12 -> 0.39748218 | D24: =D15/D12 -> 0.41363839 | E24: =E15/E12 -> 0.42039619 | F24: =F15/F12 -> 0.42522744 | G24: =G15/G12 -> 0.43322971 | H24: =H15/H12 -> 0.42897833 | I24: =I15/I12 -> 0.42392514 | J24: =J15/J12 -> 0.41807081 | ... M24: =M15/M12 -> 0.4196368
B25: Return on assets (annualised) | C25: =C21/AVERAGE(Baseline!C15,Baseline!D15) -> 0.022333359 | D25: =D21*4/AVERAGE(Balance_Sheet!C18,Balance_Sheet!D18) -> 0.016127465 | E25: =E21*4/AVERAGE(Balance_Sheet!D18,Balance_Sheet!E18) -> 0.013139342 | F25: =F21*4/AVERAGE(Balance_Sheet!E18,Balance_Sheet!F18) -> 0.012840719 | G25: =G21*4/AVERAGE(Balance_Sheet!F18,Balance_Sheet!G18) -> 0.012067542 | H25: =H21*4/AVERAGE(Balance_Sheet!G18,Balance_Sheet!H18) -> 0.013628041 | I25: =I21*4/AVERAGE(Balance_Sheet!H18,Balance_Sheet!I18) -> 0.014421527 | J25: =J21*4/AVERAGE(Balance_Sheet!I18,Balance_Sheet!J18) -> 0.016909326 | K25: =K21*4/AVERAGE(Balance_Sheet!J18,Balance_Sheet!K18) -> 0.01814272 | L25: =L21/AVERAGE(Balance_Sheet!C18,Balance_Sheet!G18) -> 0.013526606 | M25: =M21/AVERAGE(Balance_Sheet!G18,Balance_Sheet!K18) -> 0.015768183
B26: Return on equity (annualised) | C26: =C21/AVERAGE(Balance_Sheet!C10-C21+7850,Balance_Sheet!C10) -> 0.1514322 | D26: =D21*4/AVERAGE(Balance_Sheet!C10,Balance_Sheet!D10) -> 0.10843951 | E26: =E21*4/AVERAGE(Balance_Sheet!D10,Balance_Sheet!E10) -> 0.089098251 | F26: =F21*4/AVERAGE(Balance_Sheet!E10,Balance_Sheet!F10) -> 0.087857215 | G26: =G21*4/AVERAGE(Balance_Sheet!F10,Balance_Sheet!G10) -> 0.082435129 | H26: =H21*4/AVERAGE(Balance_Sheet!G10,Balance_Sheet!H10) -> 0.092900074 | I26: =I21*4/AVERAGE(Balance_Sheet!H10,Balance_Sheet!I10) -> 0.098850181 | J26: =J21*4/AVERAGE(Balance_Sheet!I10,Balance_Sheet!J10) -> 0.11643295 | K26: =K21*4/AVERAGE(Balance_Sheet!J10,Balance_Sheet!K10) -> 0.12433295 | L26: =L21/AVERAGE(Balance_Sheet!C10,Balance_Sheet!G10) -> 0.091738181 | M26: =M21/AVERAGE(Balance_Sheet!G10,Balance_Sheet!K10) -> 0.1077188 | N26: FY26 opening equity ≈ closing − PAT + FY25 dividend paid (₹11 × ~714 cr shares)
B27: Fee & other income ÷ operating income | C27: =(C10+C11)/C12 -> 0.25883383 | D27: =(D10+D11)/D12 -> 0.24347013 | E27: =(E10+E11)/E12 -> 0.24970198 | F27: =(F10+F11)/F12 -> 0.24928993 | G27: =(G10+G11)/G12 -> 0.2372546 | H27: =(H10+H11)/H12 -> 0.23147331 | I27: =(I10+I11)/I12 -> 0.23924422 | J27: =(J10+J11)/J12 -> 0.243989 | ... M27: =(M10+M11)/M12 -> 0.23902586

Sheet Balance_Sheet
A1: BALANCE SHEET (QUARTER-END)
A2: Investments are the balancing asset (surplus funds go to government securities). Equity rolls forward: opening + PAT − dividend.
B4: Particulars | C4: Mar-26 / FY26 (A) | D4: Y1 Q1 | E4: Y1 Q2 | F4: Y1 Q3 | G4: Y1 Q4 | H4: Y2 Q1 | I4: Y2 Q2 | J4: Y2 Q3 | K4: Y2 Q4 | L4: Sim Year 1 | M4: Sim Year 2 | N4: Basis / note
B5: LIABILITIES & EQUITY
B6: Deposits | C6: =Funding!C6 -> 1794625 | D6: =Funding!D6 -> 1841644.2 | E6: =Funding!E6 -> 1886948.6 | F6: =Funding!F6 -> 1930725.8 | G6: =Funding!G6 -> 1975132.5 | H6: =Funding!H6 -> 2021350.6 | I6: =Funding!I6 -> 2071884.4 | J6: =Funding!J6 -> 2126996.5 | K6: =Funding!K6 -> 2185701.6 | L6: =G6 -> 1975132.5 | M6: =K6 -> 2185701.6
B7: Borrowings | C7: =Funding!C15 -> 100000 | D7: =Funding!D15 -> 100000 | E7: =Funding!E15 -> 100000 | F7: =Funding!F15 -> 100000 | G7: =Funding!G15 -> 100000 | H7: =Funding!H15 -> 100000 | I7: =Funding!I15 -> 100000 | J7: =Funding!J15 -> 100000 | K7: =Funding!K15 -> 100000 | L7: =G7 -> 100000 | M7: =K7 -> 100000
B8: Other liabilities (excl. contingency provisions) | C8: =C11-C6-C7-C9-C10 -> 112506 | D8: =C8 -> 112506 | E8: =D8 -> 112506 | F8: =E8 -> 112506 | G8: =F8 -> 112506 | H8: =G8 -> 112506 | I8: =H8 -> 112506 | J8: =I8 -> 112506 | K8: =J8 -> 112506 | L8: =G8 -> 112506 | M8: =K8 -> 112506 | N8: Opening D = reported total − other lines; held flat
B9: Contingency provisions | C9: =NPA_Provisions!C31 -> 13100 | D9: =NPA_Provisions!D31 -> 14100 | E9: =NPA_Provisions!E31 -> 14600 | F9: =NPA_Provisions!F31 -> 13100 | G9: =NPA_Provisions!G31 -> 10100 | H9: =NPA_Provisions!H31 -> 8100 | I9: =NPA_Provisions!I31 -> 8100 | J9: =NPA_Provisions!J31 -> 8600 | K9: =NPA_Provisions!K31 -> 9600 | L9: =G9 -> 10100 | M9: =K9 -> 9600
B10: Net worth (capital + reserves) | C10: 352300 | D10: =C10+'P&L'!D21-Decisions!D25 -> 361982.05 | E10: =D10+'P&L'!E21-Decisions!E25 -> 361471.35 | F10: =E10+'P&L'!F21-Decisions!F25 -> 369498.98 | G10: =F10+'P&L'!G21-Decisions!G25 -> 377193.19 | H10: =G10+'P&L'!H21-Decisions!H25 -> 386056.43 | I10: =H10+'P&L'!I21-Decisions!I25 -> 388486.9 | J10: =I10+'P&L'!J21-Decisions!J25 -> 399962.08 | K10: =J10+'P&L'!K21-Decisions!K25 -> 412590.46 | L10: =G10 -> 377193.19 | M10: =K10 -> 412590.46 | N10: Opening E ≈ FY25 net worth + FY26 PAT − FY25 dividend; consistent with CET-1 16.35%
B11: TOTAL LIABILITIES & EQUITY | C11: =Baseline!D15 -> 2372531 | D11: =SUM(D6:D10) -> 2430232.2 | E11: =SUM(E6:E10) -> 2475526 | F11: =SUM(F6:F10) -> 2525830.8 | G11: =SUM(G6:G10) -> 2574931.7 | H11: =SUM(H6:H10) -> 2628013.1 | I11: =SUM(I6:I10) -> 2680977.3 | J11: =SUM(J6:J10) -> 2748064.6 | K11: =SUM(K6:K10) -> 2820398.1 | L11: =G11 -> 2574931.7 | M11: =K11 -> 2820398.1
B12: ASSETS
B13: Cash & balances with RBI and banks (7.5% of deposits) | C13: =C6*0.075 -> 134596.88 | D13: =D6*0.075 -> 138123.31 | E13: =E6*0.075 -> 141521.15 | F13: =F6*0.075 -> 144804.44 | G13: =G6*0.075 -> 148134.94 | H13: =H6*0.075 -> 151601.3 | I13: =I6*0.075 -> 155391.33 | J13: =J6*0.075 -> 159524.74 | K13: =K6*0.075 -> 163927.62 | L13: =G13 -> 148134.94 | M13: =K13 -> 163927.62 | N13: E – CRR 3% + operating liquidity
B14: Investments (balancing item) | C14: =C11-C13-C15-C16-C17 -> 530041.12 | D14: =D11-D13-D15-D16-D17 -> 557662.57 | E14: =E11-E13-E15-E16-E17 -> 580352.68 | F14: =F11-F13-F15-F16-F17 -> 614340.53 | G14: =G11-G13-G15-G16-G17 -> 644407.74 | H14: =H11-H13-H15-H16-H17 -> 672290.75 | I14: =I11-I13-I15-I16-I17 -> 694277.03 | J14: =J11-J13-J15-J16-J17 -> 723783.88 | K14: =K11-K13-K15-K16-K17 -> 753260.09 | L14: =G14 -> 644407.74 | M14: =K14 -> 753260.09
B15: Net advances | C15: =Loan_Book!C11 -> 1553893 | D15: =Loan_Book!D11 -> 1580371.3 | E15: =Loan_Book!E11 -> 1599502.2 | F15: =Loan_Book!F11 -> 1612460.8 | G15: =Loan_Book!G11 -> 1628089 | H15: =Loan_Book!H11 -> 1649746 | I15: =Loan_Book!I11 -> 1676858.9 | J15: =Loan_Book!J11 -> 1710231 | K15: =Loan_Book!K11 -> 1748610.4 | L15: =G15 -> 1628089 | M15: =K15 -> 1748610.4
B16: Fixed assets | C16: 14000 | D16: =C16+75 -> 14075 | E16: =D16+75 -> 14150 | F16: =E16+75 -> 14225 | G16: =F16+75 -> 14300 | H16: =G16+75 -> 14375 | I16: =H16+75 -> 14450 | J16: =I16+75 -> 14525 | K16: =J16+75 -> 14600 | L16: =G16 -> 14300 | M16: =K16 -> 14600 | N16: E – slower branch build-out
B17: Other assets | C17: 140000 | D17: =C17 -> 140000 | E17: =D17 -> 140000 | F17: =E17 -> 140000 | G17: =F17 -> 140000 | H17: =G17 -> 140000 | I17: =H17 -> 140000 | J17: =I17 -> 140000 | K17: =J17 -> 140000 | L17: =G17 -> 140000 | M17: =K17 -> 140000 | N17: E
B18: TOTAL ASSETS | C18: =SUM(C13:C17) -> 2372531 | D18: =SUM(D13:D17) -> 2430232.2 | E18: =SUM(E13:E17) -> 2475526 | F18: =SUM(F13:F17) -> 2525830.8 | G18: =SUM(G13:G17) -> 2574931.7 | H18: =SUM(H13:H17) -> 2628013.1 | I18: =SUM(I13:I17) -> 2680977.3 | J18: =SUM(J13:J17) -> 2748064.6 | K18: =SUM(K13:K17) -> 2820398.1 | L18: =G18 -> 2574931.7 | M18: =K18 -> 2820398.1
B19: Balance check (should be 0) | C19: =ROUND(C18-C11,2) -> 0 | D19: =ROUND(D18-D11,2) -> 0 | E19: =ROUND(E18-E11,2) -> 0 | F19: =ROUND(F18-F11,2) -> 0 | G19: =ROUND(G18-G11,2) -> 0 | H19: =ROUND(H18-H11,2) -> 0 | I19: =ROUND(I18-I11,2) -> 0 | J19: =ROUND(J18-J11,2) -> 0 | K19: =ROUND(K18-K11,2) -> 0 | L19: =G19 -> 0 | M19: =K19 -> 0
B20: LIQUIDITY
B21: Investments ÷ deposits (SLR headroom; min 18%) | C21: =C14/C6 -> 0.29534924 | D21: =D14/D6 -> 0.30280691 | E21: =E14/E6 -> 0.30756146 | F21: =F14/F6 -> 0.31819149 | G21: =G14/G6 -> 0.32626051 | H21: =H14/H6 -> 0.33259482 | I21: =I14/I6 -> 0.33509448 | J21: =J14/J6 -> 0.34028447 | K21: =K14/K6 -> 0.3446308 | L21: =G21 -> 0.32626051 | M21: =K21 -> 0.3446308
B22: Liquid assets ÷ total assets | C22: =(C13+C14)/C18 -> 0.28013881 | D22: =(D13+D14)/D18 -> 0.28630428 | E22: =(E13+E14)/E18 -> 0.29160422 | F22: =(F13+F14)/F18 -> 0.30055258 | G22: =(G13+G14)/G18 -> 0.30779173 | H22: =(H13+H14)/H18 -> 0.31350379 | I22: =(I13+I14)/I18 -> 0.31692486 | J22: =(J13+J14)/J18 -> 0.32142935 | K22: =(K13+K14)/K18 -> 0.32519796 | L22: =G22 -> 0.30779173 | M22: =K22 -> 0.32519796
B23: Investment yield (annual) | C23: 0.066 | D23: =$C23+Market!$C$22*Market!D8 -> 0.066 | E23: =$C23+Market!$C$22*Market!E8 -> 0.065125 | F23: =$C23+Market!$C$22*Market!F8 -> 0.06425 | G23: =$C23+Market!$C$22*Market!G8 -> 0.063375 | H23: =$C23+Market!$C$22*Market!H8 -> 0.063375 | I23: =$C23+Market!$C$22*Market!I8 -> 0.063375 | J23: =$C23+Market!$C$22*Market!J8 -> 0.063375 | K23: =$C23+Market!$C$22*Market!K8 -> 0.06425 | L23: =AVERAGE(D23:G23) -> 0.0646875 | M23: =AVERAGE(H23:K23) -> 0.06359375 | N23: E
B24: Average investments | D24: =AVERAGE(C14,D14) -> 543851.85 | E24: =AVERAGE(D14,E14) -> 569007.63 | F24: =AVERAGE(E14,F14) -> 597346.61 | G24: =AVERAGE(F14,G14) -> 629374.14 | H24: =AVERAGE(G14,H14) -> 658349.24 | I24: =AVERAGE(H14,I14) -> 683283.89 | J24: =AVERAGE(I14,J14) -> 709030.45 | K24: =AVERAGE(J14,K14) -> 738521.99 | L24: =AVERAGE(D24:G24) -> 584895.05 | M24: =AVERAGE(H24:K24) -> 697296.39

Sheet Capital_RAROC
A1: CAPITAL ADEQUACY & RISK-ADJUSTED RETURN ON CAPITAL (RAROC)
A2: RAROC = (PPOP − expected loss) × (1 − tax) ÷ economic capital. Economic capital = RWA × 12%. Hurdle = 14% cost of equity.
B4: Particulars | C4: Mar-26 / FY26 (A) | D4: Y1 Q1 | E4: Y1 Q2 | F4: Y1 Q3 | G4: Y1 Q4 | H4: Y2 Q1 | I4: Y2 Q2 | J4: Y2 Q3 | K4: Y2 Q4 | L4: Sim Year 1 | M4: Sim Year 2 | N4: Basis / note
B5: RISK-WEIGHTED ASSETS
B6: RWA – Secured retail (mortgages, auto, gold) | C6: 0.6 | D6: =Loan_Book!D6*$C6 -> 365177.29 | E6: =Loan_Book!E6*$C6 -> 371750.48 | F6: =Loan_Book!F6*$C6 -> 377326.73 | G6: =Loan_Book!G6*$C6 -> 382986.64 | H6: =Loan_Book!H6*$C6 -> 389880.39 | I6: =Loan_Book!I6*$C6 -> 397678 | J6: =Loan_Book!J6*$C6 -> 406824.6 | K6: =Loan_Book!K6*$C6 -> 416995.21 | L6: =G6 -> 382986.64 | M6: =K6 -> 416995.21 | N6: Col C = risk weight 60% (E, RBI standardised approach)
B7: RWA – Unsecured retail (personal loans, cards) | C7: 1.25 | D7: =Loan_Book!D7*$C7 -> 230753.11 | E7: =Loan_Book!E7*$C7 -> 224984.28 | F7: =Loan_Book!F7*$C7 -> 218234.75 | G7: =Loan_Book!G7*$C7 -> 213870.06 | H7: =Loan_Book!H7*$C7 -> 211731.36 | I7: =Loan_Book!I7*$C7 -> 211731.36 | J7: =Loan_Book!J7*$C7 -> 213848.67 | K7: =Loan_Book!K7*$C7 -> 217056.4 | L7: =G7 -> 213870.06 | M7: =K7 -> 217056.4 | N7: Col C = risk weight 125% (E, RBI standardised approach)
B8: RWA – Business banking & SME | C8: 0.85 | D8: =Loan_Book!D8*$C8 -> 261361.69 | E8: =Loan_Book!E8*$C8 -> 263975.31 | F8: =Loan_Book!F8*$C8 -> 265295.19 | G8: =Loan_Book!G8*$C8 -> 266621.66 | H8: =Loan_Book!H8*$C8 -> 269287.88 | I8: =Loan_Book!I8*$C8 -> 273327.2 | J8: =Loan_Book!J8*$C8 -> 278793.74 | K8: =Loan_Book!K8*$C8 -> 285763.59 | L8: =G8 -> 266621.66 | M8: =K8 -> 285763.59 | N8: Col C = risk weight 85% (E, RBI standardised approach)
B9: RWA – Rural & agri | C9: 0.9 | D9: =Loan_Book!D9*$C9 -> 81924.347 | E9: =Loan_Book!E9*$C9 -> 81924.347 | F9: =Loan_Book!F9*$C9 -> 81514.725 | G9: =Loan_Book!G9*$C9 -> 81514.725 | H9: =Loan_Book!H9*$C9 -> 81922.299 | I9: =Loan_Book!I9*$C9 -> 82741.522 | J9: =Loan_Book!J9*$C9 -> 83982.644 | K9: =Loan_Book!K9*$C9 -> 85662.297 | L9: =G9 -> 81514.725 | M9: =K9 -> 85662.297 | N9: Col C = risk weight 90% (E, RBI standardised approach)
B10: RWA – Corporate & wholesale | C10: 0.7 | D10: =Loan_Book!D10*$C10 -> 272040.05 | E10: =Loan_Book!E10*$C10 -> 278841.05 | F10: =Loan_Book!F10*$C10 -> 284417.87 | G10: =Loan_Book!G10*$C10 -> 290106.23 | H10: =Loan_Book!H10*$C10 -> 295908.35 | I10: =Loan_Book!I10*$C10 -> 301826.52 | J10: =Loan_Book!J10*$C10 -> 307863.05 | K10: =Loan_Book!K10*$C10 -> 314020.31 | L10: =G10 -> 290106.23 | M10: =K10 -> 314020.31 | N10: Col C = risk weight 70% (E, RBI standardised approach)
B11: RWA – investments (15%) and other & fixed assets (100%) | C11: =Balance_Sheet!C14*0.15+Balance_Sheet!C16+Balance_Sheet!C17 -> 233506.17 | D11: =Balance_Sheet!D14*0.15+Balance_Sheet!D16+Balance_Sheet!D17 -> 237724.39 | E11: =Balance_Sheet!E14*0.15+Balance_Sheet!E16+Balance_Sheet!E17 -> 241202.9 | F11: =Balance_Sheet!F14*0.15+Balance_Sheet!F16+Balance_Sheet!F17 -> 246376.08 | G11: =Balance_Sheet!G14*0.15+Balance_Sheet!G16+Balance_Sheet!G17 -> 250961.16 | H11: =Balance_Sheet!H14*0.15+Balance_Sheet!H16+Balance_Sheet!H17 -> 255218.61 | I11: =Balance_Sheet!I14*0.15+Balance_Sheet!I16+Balance_Sheet!I17 -> 258591.55 | J11: =Balance_Sheet!J14*0.15+Balance_Sheet!J16+Balance_Sheet!J17 -> 263092.58 | K11: =Balance_Sheet!K14*0.15+Balance_Sheet!K16+Balance_Sheet!K17 -> 267589.01 | L11: =G11 -> 250961.16 | M11: =K11 -> 267589.01
B12: Credit RWA | C12: =SUMPRODUCT(Loan_Book!C6:C10,C6:C10)+C11 -> 1427362.2 | D12: =SUM(D6:D11) -> 1448980.9 | E12: =SUM(E6:E11) -> 1462678.4 | F12: =SUM(F6:F11) -> 1473165.4 | G12: =SUM(G6:G11) -> 1486060.5 | H12: =SUM(H6:H11) -> 1503948.9 | I12: =SUM(I6:I11) -> 1525896.2 | J12: =SUM(J6:J11) -> 1554405.3 | K12: =SUM(K6:K11) -> 1587086.8 | L12: =G12 -> 1486060.5 | M12: =K12 -> 1587086.8
B13: Operational & market risk RWA (% of credit RWA, calibrated) | C13: =(C16/Baseline!D23-C12)/C12 -> 0.46430802 | D13: =D12*$C13 -> 672773.44 | E13: =E12*$C13 -> 679133.3 | F13: =F12*$C13 -> 684002.49 | G13: =G12*$C13 -> 689989.8 | H13: =H12*$C13 -> 698295.53 | I13: =I12*$C13 -> 708485.82 | J13: =J12*$C13 -> 721722.84 | K13: =K12*$C13 -> 736897.14 | L13: =G13 -> 689989.8 | M13: =K13 -> 736897.14 | N13: Col C calibrated so that opening CET-1 = reported 16.35% (D)
B14: TOTAL RWA | C14: =C12*(1+C13) -> 2090097.9 | D14: =D12+D13 -> 2121754.3 | E14: =E12+E13 -> 2141811.7 | F14: =F12+F13 -> 2157167.8 | G14: =G12+G13 -> 2176050.3 | H14: =H12+H13 -> 2202244.4 | I14: =I12+I13 -> 2234382 | J14: =J12+J13 -> 2276128.1 | K14: =K12+K13 -> 2323984 | L14: =G14 -> 2176050.3 | M14: =K14 -> 2323984
B15: CAPITAL
B16: CET-1 capital (net worth − 3% deductions) | C16: =Balance_Sheet!C10*0.97 -> 341731 | D16: =Balance_Sheet!D10*0.97 -> 351122.59 | E16: =Balance_Sheet!E10*0.97 -> 350627.21 | F16: =Balance_Sheet!F10*0.97 -> 358414.01 | G16: =Balance_Sheet!G10*0.97 -> 365877.39 | H16: =Balance_Sheet!H10*0.97 -> 374474.74 | I16: =Balance_Sheet!I10*0.97 -> 376832.29 | J16: =Balance_Sheet!J10*0.97 -> 387963.22 | K16: =Balance_Sheet!K10*0.97 -> 400212.75 | L16: =G16 -> 365877.39 | M16: =K16 -> 400212.75
B17: Tier-2 capital | C17: =(Baseline!D22-Baseline!D23)*C14 -> 17347.812 | D17: =C17 -> 17347.812 | E17: =D17 -> 17347.812 | F17: =E17 -> 17347.812 | G17: =F17 -> 17347.812 | H17: =G17 -> 17347.812 | I17: =H17 -> 17347.812 | J17: =I17 -> 17347.812 | K17: =J17 -> 17347.812 | L17: =G17 -> 17347.812 | M17: =K17 -> 17347.812 | N17: Opening = (CRAR − CET-1) × RWA (D); held flat
B18: CET-1 RATIO | C18: =C16/C14 -> 0.1635 | D18: =D16/D14 -> 0.16548692 | E18: =E16/E14 -> 0.1637059 | F18: =F16/F14 -> 0.16615027 | G18: =G16/G14 -> 0.1681383 | H18: =H16/H14 -> 0.17004231 | I18: =I16/I14 -> 0.16865169 | J18: =J16/J14 -> 0.17044876 | K18: =K16/K14 -> 0.17220977 | L18: =G18 -> 0.1681383 | M18: =K18 -> 0.17220977
B19: TOTAL CAPITAL ADEQUACY (CRAR) | C19: =(C16+C17)/C14 -> 0.1718 | D19: =(D16+D17)/D14 -> 0.17366309 | E19: =(E16+E17)/E14 -> 0.1718055 | F19: =(F16+F17)/F14 -> 0.17419221 | G19: =(G16+G17)/G14 -> 0.17611046 | H19: =(H16+H17)/H14 -> 0.17791965 | I19: =(I16+I17)/I14 -> 0.17641572 | J19: =(J16+J17)/J14 -> 0.17807039 | K19: =(K16+K17)/K14 -> 0.17967446 | L19: =G19 -> 0.17611046 | M19: =K19 -> 0.17967446
B20: Regulatory minimum CRAR incl. buffers | C20: 0.117 | D20: =$C20 -> 0.117 | E20: =$C20 -> 0.117 | F20: =$C20 -> 0.117 | G20: =$C20 -> 0.117 | H20: =$C20 -> 0.117 | I20: =$C20 -> 0.117 | J20: =$C20 -> 0.117 | K20: =$C20 -> 0.117 | L20: =G20 -> 0.117 | M20: =K20 -> 0.117 | N20: A – ICICI disclosed requirement 11.70%
B21: Headroom over minimum (pp) | C21: =C19-C20 -> 0.0548 | D21: =D19-D20 -> 0.056663085 | E21: =E19-E20 -> 0.054805501 | F21: =F19-F20 -> 0.057192206 | G21: =G19-G20 -> 0.059110456 | H21: =H19-H20 -> 0.060919647 | I21: =I19-I20 -> 0.05941572 | J21: =J19-J20 -> 0.061070393 | K21: =K19-K20 -> 0.062674459 | L21: =G21 -> 0.059110456 | M21: =K21 -> 0.062674459
B22: RAROC
B23: Pre-provision operating profit | C23: =Baseline!D9 -> 71599 | D23: ='P&L'!D16 -> 17841.015 | E23: ='P&L'!E16 -> 17723.965 | F23: ='P&L'!F16 -> 17525.933 | G23: ='P&L'!G16 -> 16976.878 | H23: ='P&L'!H16 -> 17297.447 | I23: ='P&L'!I16 -> 17826.01 | J23: ='P&L'!J16 -> 18491.386 | K23: ='P&L'!K16 -> 19490.158 | L23: =SUM(D23:G23) -> 70067.791 | M23: =SUM(H23:K23) -> 73105.001
B24: − Expected loss | C24: =-SUMPRODUCT(Loan_Book!C6:C10,NPA_Provisions!C6:C10,NPA_Provisions!C34:C38) -> -10447.91 | D24: =-NPA_Provisions!D39 -> -3483.371 | E24: =-NPA_Provisions!E39 -> -4715.7477 | F24: =-NPA_Provisions!F39 -> -5749.5495 | G24: =-NPA_Provisions!G39 -> -6590.8717 | H24: =-NPA_Provisions!H39 -> -5928.7024 | I24: =-NPA_Provisions!I39 -> -5031.6189 | J24: =-NPA_Provisions!J39 -> -4026.2746 | K24: =-NPA_Provisions!K39 -> -3450.0013 | L24: =SUM(D24:G24) -> -20539.54 | M24: =SUM(H24:K24) -> -18436.597
B25: Risk-adjusted profit after tax | C25: =(C23+C24)*(1-Market!$C$29) -> 45759.36 | D25: =(D23+D24)*(1-Market!$C$29) -> 10743.825 | E25: =(E23+E24)*(1-Market!$C$29) -> 9734.0488 | F25: =(F23+F24)*(1-Market!$C$29) -> 8812.2675 | G25: =(G23+G24)*(1-Market!$C$29) -> 7771.8488 | H25: =(H23+H24)*(1-Market!$C$29) -> 8507.2319 | I25: =(I23+I24)*(1-Market!$C$29) -> 9574.0428 | J25: =(J23+J24)*(1-Market!$C$29) -> 10824.243 | K25: =(K23+K24)*(1-Market!$C$29) -> 12002.849 | L25: =SUM(D25:G25) -> 37061.99 | M25: =SUM(H25:K25) -> 40908.367
B26: Economic capital ratio | C26: 0.12 | D26: =$C26 -> 0.12 | E26: =$C26 -> 0.12 | F26: =$C26 -> 0.12 | G26: =$C26 -> 0.12 | H26: =$C26 -> 0.12 | I26: =$C26 -> 0.12 | J26: =$C26 -> 0.12 | K26: =$C26 -> 0.12 | L26: =G26 -> 0.12 | M26: =K26 -> 0.12 | N26: E – internal capital allocated per ₹ of RWA
B27: Economic capital | C27: =C14*C26 -> 250811.74 | D27: =D14*D26 -> 254610.52 | E27: =E14*E26 -> 257017.4 | F27: =F14*F26 -> 258860.14 | G27: =G14*G26 -> 261126.03 | H27: =H14*H26 -> 264269.33 | I27: =I14*I26 -> 268125.84 | J27: =J14*J26 -> 273135.38 | K27: =K14*K26 -> 278878.08 | L27: =AVERAGE(D27:G27) -> 257903.52 | M27: =AVERAGE(H27:K27) -> 271102.16
B28: RAROC (annualised) | C28: =C25/C27 -> 0.18244505 | D28: =D25*4/D27 -> 0.1687884 | E28: =E25*4/E27 -> 0.15149245 | F28: =F25*4/F27 -> 0.13617033 | G28: =G25*4/G27 -> 0.11905131 | H28: =H25*4/H27 -> 0.12876609 | I28: =I25*4/I27 -> 0.1428291 | J28: =J25*4/J27 -> 0.15851836 | K28: =K25*4/K27 -> 0.1721591 | L28: =L25/L27 -> 0.14370486 | M28: =M25/M27 -> 0.1508965
B29: Hurdle rate (cost of equity) | C29: 0.14 | D29: =$C29 -> 0.14 | E29: =$C29 -> 0.14 | F29: =$C29 -> 0.14 | G29: =$C29 -> 0.14 | H29: =$C29 -> 0.14 | I29: =$C29 -> 0.14 | J29: =$C29 -> 0.14 | K29: =$C29 -> 0.14 | ... M29: =$C29 -> 0.14 | N29: E – ICICI cost of equity ~13–14%
B30: RAROC spread over hurdle (pp) | C30: =C28-C29 -> 0.042445047 | D30: =D28-D29 -> 0.028788395 | E30: =E28-E29 -> 0.011492448 | F30: =F28-F29 -> -0.0038296724 | G30: =G28-G29 -> -0.020948693 | H30: =H28-H29 -> -0.011233913 | I30: =I28-I29 -> 0.0028290967 | J30: =J28-J29 -> 0.018518356 | ... M30: =M28-M29 -> 0.010896501
B31: Economic value added (₹ cr) | C31: =C25-C27*C29 -> 10645.716 | D31: =D25-D27*D29/4 -> 1832.4571 | E31: =E25-E27*E29/4 -> 738.43981 | F31: =F25-F27*F29/4 -> -247.83738 | G31: =G25-G27*G29/4 -> -1367.5623 | H31: =H25-H27*H29/4 -> -742.19468 | I31: =I25-I27*I29/4 -> 189.63848 | J31: =J25-J27*J29/4 -> 1264.5045 | K31: =K25-K27*K29/4 -> 2242.1167 | L31: =SUM(D31:G31) -> 955.49718 | M31: =SUM(H31:K31) -> 2954.065

Sheet Segment_RAROC
A1: SEGMENT RAROC | WHERE DOES EACH ₹ OF CAPITAL EARN THE MOST?
A2: Annual view at peak stress (Y1 Q4 conditions) vs normal (FY26). Drives the capital-allocation decision on the Decisions sheet.
B4: Segment | C4: Yield | D4: Funds cost (FTP) | E4: Fee yield | F4: Opex % | G4: PD normal | H4: LGD | I4: Risk weight | J4: RAROC normal | K4: PD stress | L4: RAROC stress | M4: vs 14% hurdle
B5: Secured retail (mortgages, auto, gold) | C5: =Loan_Book!C22 -> 0.087 | D5: =Funding!C13+0.005 -> 0.052096 | E5: 0.004 | F5: 0.012 | G5: =NPA_Provisions!C6 -> 0.01 | H5: =NPA_Provisions!C34 -> 0.25 | I5: =Capital_RAROC!C6 -> 0.6 | J5: =(C5-D5+E5-F5-G5*H5)*(1-Market!$C$29)/(I5*Capital_RAROC!$C$26*(1+Capital_RAROC!$C$13)) -> 0.17320955 | K5: =G5*Market!$G$10*(1-Decisions!$G$19) -> 0.0255 | L5: =(Loan_Book!G22-(Funding!G13+0.005)+E5-F5-K5*H5)*(1-Market!$C$29)/(I5*Capital_RAROC!$C$26*(1+Capital_RAROC!$C$13)) -> 0.1133303 | M5: =IF(L5>=0.14,"Above hurdle – grow",IF(L5>=0,"Below hurdle – reprice","Destroys value – shrink")) -> Below hurdle – reprice
B6: Unsecured retail (personal loans, cards) | C6: =Loan_Book!C23 -> 0.147 | D6: =Funding!C13+0.005 -> 0.052096 | E6: 0.015 | F6: 0.035 | G6: =NPA_Provisions!C7 -> 0.04 | H6: =NPA_Provisions!C35 -> 0.65 | I6: =Capital_RAROC!C7 -> 1.25 | J6: =(C6-D6+E6-F6-G6*H6)*(1-Market!$C$29)/(I6*Capital_RAROC!$C$26*(1+Capital_RAROC!$C$13)) -> 0.16660822 | K6: =G6*Market!$G$10*(1-Decisions!$G$19) -> 0.102 | L6: =(Loan_Book!G23-(Funding!G13+0.005)+E6-F6-K6*H6)*(1-Market!$C$29)/(I6*Capital_RAROC!$C$26*(1+Capital_RAROC!$C$13)) -> 0.049543793 | M6: =IF(L6>=0.14,"Above hurdle – grow",IF(L6>=0,"Below hurdle – reprice","Destroys value – shrink")) -> Below hurdle – reprice
B7: Business banking & SME | C7: =Loan_Book!C24 -> 0.097 | D7: =Funding!C13+0.005 -> 0.052096 | E7: 0.01 | F7: 0.018 | G7: =NPA_Provisions!C8 -> 0.02 | H7: =NPA_Provisions!C36 -> 0.4 | I7: =Capital_RAROC!C8 -> 0.85 | J7: =(C7-D7+E7-F7-G7*H7)*(1-Market!$C$29)/(I7*Capital_RAROC!$C$26*(1+Capital_RAROC!$C$13)) -> 0.14481084 | K7: =G7*Market!$G$10*(1-Decisions!$G$19) -> 0.051 | L7: =(Loan_Book!G24-(Funding!G13+0.005)+E7-F7-K7*H7)*(1-Market!$C$29)/(I7*Capital_RAROC!$C$26*(1+Capital_RAROC!$C$13)) -> 0.089892731 | M7: =IF(L7>=0.14,"Above hurdle – grow",IF(L7>=0,"Below hurdle – reprice","Destroys value – shrink")) -> Below hurdle – reprice
B8: Rural & agri | C8: =Loan_Book!C25 -> 0.102 | D8: =Funding!C13+0.005 -> 0.052096 | E8: 0.005 | F8: 0.025 | G8: =NPA_Provisions!C9 -> 0.025 | H8: =NPA_Provisions!C37 -> 0.45 | I8: =Capital_RAROC!C9 -> 0.9 | J8: =(C8-D8+E8-F8-G8*H8)*(1-Market!$C$29)/(I8*Capital_RAROC!$C$26*(1+Capital_RAROC!$C$13)) -> 0.088265609 | K8: =G8*Market!$G$10*(1-Decisions!$G$19) -> 0.06375 | L8: =(Loan_Book!G25-(Funding!G13+0.005)+E8-F8-K8*H8)*(1-Market!$C$29)/(I8*Capital_RAROC!$C$26*(1+Capital_RAROC!$C$13)) -> -0.011096192 | M8: =IF(L8>=0.14,"Above hurdle – grow",IF(L8>=0,"Below hurdle – reprice","Destroys value – shrink")) -> Destroys value – shrink
B9: Corporate & wholesale | C9: =Loan_Book!C26 -> 0.077 | D9: =Funding!C13+0.005 -> 0.052096 | E9: 0.008 | F9: 0.005 | G9: =NPA_Provisions!C10 -> 0.004 | H9: =NPA_Provisions!C38 -> 0.45 | I9: =Capital_RAROC!C10 -> 0.7 | J9: =(C9-D9+E9-F9-G9*H9)*(1-Market!$C$29)/(I9*Capital_RAROC!$C$26*(1+Capital_RAROC!$C$13)) -> 0.15880753 | K9: =G9*Market!$G$10*(1-Decisions!$G$19) -> 0.0102 | L9: =(Loan_Book!G26-(Funding!G13+0.005)+E9-F9-K9*H9)*(1-Market!$C$29)/(I9*Capital_RAROC!$C$26*(1+Capital_RAROC!$C$13)) -> 0.12016686 | M9: =IF(L9>=0.14,"Above hurdle – grow",IF(L9>=0,"Below hurdle – reprice","Destroys value – shrink")) -> Below hurdle – reprice
B11: Formula: [yield − funds-transfer price + fee yield − opex − PD × LGD] × (1 − tax) ÷ [risk weight × 12% × (1 + op-risk load)]. Stress uses Y1 Q4 default multiplier after our underwriting tightening.

Sheet Market_Share
A1: MARKET SHARE (% OF TOTAL INDIAN BANKING MARKET)
A2: System totals grow with the Market sheet; ICICI balances come from the model.
B4: Particulars | C4: Mar-26 (A/E) | D4: Y1 Q1 | E4: Y1 Q2 | F4: Y1 Q3 | G4: Y1 Q4 | H4: Y2 Q1 | I4: Y2 Q2 | J4: Y2 Q3 | K4: Y2 Q4 | L4: Sim Year 1 | M4: Sim Year 2 | N4: Basis / note
B5: System deposits (₹ cr) | C5: =Market!C27 -> 26229916 | D5: =C5*(1+Market!D12) -> 26885664 | E5: =D5*(1+Market!E12) -> 27477149 | F5: =E5*(1+Market!F12) -> 28026691 | G5: =F5*(1+Market!G12) -> 28587225 | H5: =G5*(1+Market!H12) -> 29187557 | I5: =H5*(1+Market!I12) -> 29858871 | J5: =I5*(1+Market!J12) -> 30605343 | K5: =J5*(1+Market!K12) -> 31401082 | L5: =G5 -> 28587225 | M5: =K5 -> 31401082
B6: ICICI deposits (₹ cr) | C6: =Funding!C6 -> 1794625 | D6: =Funding!D6 -> 1841644.2 | E6: =Funding!E6 -> 1886948.6 | F6: =Funding!F6 -> 1930725.8 | G6: =Funding!G6 -> 1975132.5 | H6: =Funding!H6 -> 2021350.6 | I6: =Funding!I6 -> 2071884.4 | J6: =Funding!J6 -> 2126996.5 | K6: =Funding!K6 -> 2185701.6 | L6: =G6 -> 1975132.5 | M6: =K6 -> 2185701.6
B7: ICICI DEPOSIT MARKET SHARE | C7: =C6/C5 -> 0.068419014 | D7: =D6/D5 -> 0.068499115 | E7: =E6/E5 -> 0.068673379 | F7: =F6/F5 -> 0.068888824 | G7: =G6/G5 -> 0.069091439 | H7: =H6/H5 -> 0.069253848 | I7: =I6/I5 -> 0.069389241 | J7: =J6/J5 -> 0.069497556 | K7: =K6/K5 -> 0.069605934 | L7: =G7 -> 0.069091439 | M7: =K7 -> 0.069605934
B8: System bank credit (₹ cr) | C8: =Market!C28 -> 20600000 | D8: =C8*(1+Market!D13) -> 21012000 | E8: =D8*(1+Market!E13) -> 21327180 | F8: =E8*(1+Market!F13) -> 21540452 | G8: =F8*(1+Market!G13) -> 21712775 | H8: =G8*(1+Market!H13) -> 21929903 | I8: =H8*(1+Market!I13) -> 22236922 | J8: =I8*(1+Market!J13) -> 22637186 | K8: =J8*(1+Market!K13) -> 23135205 | L8: =G8 -> 21712775 | M8: =K8 -> 23135205
B9: ICICI gross advances (₹ cr) | C9: =NPA_Provisions!C23 -> 1570559.8 | D9: =NPA_Provisions!D23 -> 1599075.5 | E9: =NPA_Provisions!E23 -> 1622591.1 | F9: =NPA_Provisions!F23 -> 1641365.7 | G9: =NPA_Provisions!G23 -> 1663622.9 | H9: =NPA_Provisions!H23 -> 1689001.7 | I9: =NPA_Provisions!I23 -> 1717016.3 | J9: =NPA_Provisions!J23 -> 1748792.6 | K9: =NPA_Provisions!K23 -> 1784677.5 | L9: =G9 -> 1663622.9 | M9: =K9 -> 1784677.5
B10: ICICI CREDIT MARKET SHARE | C10: =C9/C8 -> 0.076240766 | D10: =D9/D8 -> 0.076102963 | E10: =E9/E8 -> 0.076080904 | F10: =F9/F8 -> 0.076199223 | G10: =G9/G8 -> 0.076619541 | H10: =H9/H8 -> 0.077018201 | I10: =I9/I8 -> 0.077214659 | J10: =J9/J8 -> 0.077253088 | K10: =K9/K8 -> 0.077141201 | L10: =G10 -> 0.076619541 | M10: =K10 -> 0.077141201
B11: Change in deposit share since opening (bp) | D11: =(D7-$C7)*10000 -> 0.8010031 | E11: =(E7-$C7)*10000 -> 2.543642 | F11: =(F7-$C7)*10000 -> 4.698101 | G11: =(G7-$C7)*10000 -> 6.7242429 | H11: =(H7-$C7)*10000 -> 8.3483315 | I11: =(I7-$C7)*10000 -> 9.7022679 | J11: =(J7-$C7)*10000 -> 10.785417 | K11: =(K7-$C7)*10000 -> 11.8692 | L11: =(G7-$C7)*10000 -> 6.7242429 | M11: =(K7-$C7)*10000 -> 11.8692
B12: Change in credit share since opening (bp) | D12: =(D10-$C10)*10000 -> -1.3780274 | E12: =(E10-$C10)*10000 -> -1.5986193 | F12: =(F10-$C10)*10000 -> -0.41543387 | G12: =(G10-$C10)*10000 -> 3.7877533 | H12: =(H10-$C10)*10000 -> 7.7743465 | I12: =(I10-$C10)*10000 -> 9.7389266 | J12: =(J10-$C10)*10000 -> 10.123223 | K12: =(K10-$C10)*10000 -> 9.0043515 | L12: =(G10-$C10)*10000 -> 3.7877533 | M12: =(K10-$C10)*10000 -> 9.0043515

Sheet Customer_Survey
A1: CUSTOMER SATISFACTION | SIMULATED QUARTERLY SURVEY
A2: SIMULATED responses (n = 50 per round) generated from our decisions and the recession conditions, as the brief allows. Replace the count tables with real Google-Form responses if you run the survey.
B4: Question / score | C4: Round 1 | D4: Round 2 | E4: Round 3 | F4: Round 4 | G4: Round 5 | H4: Round 6 | I4: Round 7 | J4: Round 8
B5: Q1. How safe do you feel keeping your money with ICICI Bank?
B6: responses scoring 1 | C6: 0 | D6: 0 | E6: 0 | F6: 0 | G6: 0 | H6: 0 | I6: 0 | J6: 0
B7: responses scoring 2 | C7: 0 | D7: 0 | E7: 0 | F7: 0 | G7: 0 | H7: 0 | I7: 0 | J7: 0
B8: responses scoring 3 | C8: 2 | D8: 3 | E8: 3 | F8: 4 | G8: 3 | H8: 3 | I8: 2 | J8: 2
B9: responses scoring 4 | C9: 23 | D9: 24 | E9: 26 | F9: 26 | G9: 27 | H9: 24 | I9: 23 | J9: 22
B10: responses scoring 5 | C10: 25 | D10: 23 | E10: 21 | F10: 20 | G10: 20 | H10: 23 | I10: 25 | J10: 26
B11: Average score (out of 5) | C11: =(C6*1+C7*2+C8*3+C9*4+C10*5)/SUM(C6:C10) -> 4.46 | D11: =(D6*1+D7*2+D8*3+D9*4+D10*5)/SUM(D6:D10) -> 4.4 | E11: =(E6*1+E7*2+E8*3+E9*4+E10*5)/SUM(E6:E10) -> 4.36 | F11: =(F6*1+F7*2+F8*3+F9*4+F10*5)/SUM(F6:F10) -> 4.32 | G11: =(G6*1+G7*2+G8*3+G9*4+G10*5)/SUM(G6:G10) -> 4.34 | H11: =(H6*1+H7*2+H8*3+H9*4+H10*5)/SUM(H6:H10) -> 4.4 | I11: =(I6*1+I7*2+I8*3+I9*4+I10*5)/SUM(I6:I10) -> 4.46 | J11: =(J6*1+J7*2+J8*3+J9*4+J10*5)/SUM(J6:J10) -> 4.48
B13: Q2. Are our loan and deposit rates fair and clearly explained?
B14: responses scoring 1 | C14: 0 | D14: 0 | E14: 0 | F14: 0 | G14: 0 | H14: 0 | I14: 0 | J14: 0
B15: responses scoring 2 | C15: 0 | D15: 1 | E15: 1 | F15: 1 | G15: 1 | H15: 1 | I15: 0 | J15: 0
B16: responses scoring 3 | C16: 9 | D16: 13 | E16: 17 | F16: 17 | G16: 17 | H16: 13 | I16: 10 | J16: 9
B17: responses scoring 4 | C17: 31 | D17: 29 | E17: 27 | F17: 28 | G17: 27 | H17: 29 | I17: 30 | J17: 31
B18: responses scoring 5 | C18: 10 | D18: 7 | E18: 5 | F18: 4 | G18: 5 | H18: 7 | I18: 10 | J18: 10
B19: Average score (out of 5) | C19: =(C14*1+C15*2+C16*3+C17*4+C18*5)/SUM(C14:C18) -> 4.02 | D19: =(D14*1+D15*2+D16*3+D17*4+D18*5)/SUM(D14:D18) -> 3.84 | E19: =(E14*1+E15*2+E16*3+E17*4+E18*5)/SUM(E14:E18) -> 3.72 | F19: =(F14*1+F15*2+F16*3+F17*4+F18*5)/SUM(F14:F18) -> 3.7 | G19: =(G14*1+G15*2+G16*3+G17*4+G18*5)/SUM(G14:G18) -> 3.72 | H19: =(H14*1+H15*2+H16*3+H17*4+H18*5)/SUM(H14:H18) -> 3.84 | I19: =(I14*1+I15*2+I16*3+I17*4+I18*5)/SUM(I14:I18) -> 4 | J19: =(J14*1+J15*2+J16*3+J17*4+J18*5)/SUM(J14:J18) -> 4.02
B21: Q3. If you faced repayment difficulty, did we offer practical support?
B22: responses scoring 1 | C22: 0 | D22: 0 | E22: 0 | F22: 0 | G22: 0 | H22: 0 | I22: 0 | J22: 0
B23: responses scoring 2 | C23: 1 | D23: 1 | E23: 1 | F23: 1 | G23: 2 | H23: 1 | I23: 1 | J23: 1
B24: responses scoring 3 | C24: 15 | D24: 15 | E24: 16 | F24: 18 | G24: 19 | H24: 18 | I24: 17 | J24: 17
B25: responses scoring 4 | C25: 28 | D25: 28 | E25: 28 | F25: 27 | G25: 25 | H25: 27 | I25: 28 | J25: 28
B26: responses scoring 5 | C26: 6 | D26: 6 | E26: 5 | F26: 4 | G26: 4 | H26: 4 | I26: 4 | J26: 4
B27: Average score (out of 5) | C27: =(C22*1+C23*2+C24*3+C25*4+C26*5)/SUM(C22:C26) -> 3.78 | D27: =(D22*1+D23*2+D24*3+D25*4+D26*5)/SUM(D22:D26) -> 3.78 | E27: =(E22*1+E23*2+E24*3+E25*4+E26*5)/SUM(E22:E26) -> 3.74 | F27: =(F22*1+F23*2+F24*3+F25*4+F26*5)/SUM(F22:F26) -> 3.68 | G27: =(G22*1+G23*2+G24*3+G25*4+G26*5)/SUM(G22:G26) -> 3.62 | H27: =(H22*1+H23*2+H24*3+H25*4+H26*5)/SUM(H22:H26) -> 3.68 | I27: =(I22*1+I23*2+I24*3+I25*4+I26*5)/SUM(I22:I26) -> 3.7 | J27: =(J22*1+J23*2+J24*3+J25*4+J26*5)/SUM(J22:J26) -> 3.7
B29: Q4. How easy is it to get a service issue resolved (app / branch / call)?
B30: responses scoring 1 | C30: 0 | D30: 0 | E30: 0 | F30: 0 | G30: 0 | H30: 0 | I30: 0 | J30: 0
B31: responses scoring 2 | C31: 0 | D31: 0 | E31: 0 | F31: 0 | G31: 0 | H31: 0 | I31: 0 | J31: 0
B32: responses scoring 3 | C32: 6 | D32: 7 | E32: 8 | F32: 8 | G32: 9 | H32: 9 | I32: 9 | J32: 8
B33: responses scoring 4 | C33: 29 | D33: 30 | E33: 30 | F33: 31 | G33: 31 | H33: 30 | I33: 30 | J33: 31
B34: responses scoring 5 | C34: 15 | D34: 13 | E34: 12 | F34: 11 | G34: 10 | H34: 11 | I34: 11 | J34: 11
B35: Average score (out of 5) | C35: =(C30*1+C31*2+C32*3+C33*4+C34*5)/SUM(C30:C34) -> 4.18 | D35: =(D30*1+D31*2+D32*3+D33*4+D34*5)/SUM(D30:D34) -> 4.12 | E35: =(E30*1+E31*2+E32*3+E33*4+E34*5)/SUM(E30:E34) -> 4.08 | F35: =(F30*1+F31*2+F32*3+F33*4+F34*5)/SUM(F30:F34) -> 4.06 | G35: =(G30*1+G31*2+G32*3+G33*4+G34*5)/SUM(G30:G34) -> 4.02 | H35: =(H30*1+H31*2+H32*3+H33*4+H34*5)/SUM(H30:H34) -> 4.04 | I35: =(I30*1+I31*2+I32*3+I33*4+I34*5)/SUM(I30:I34) -> 4.04 | J35: =(J30*1+J31*2+J32*3+J33*4+J34*5)/SUM(J30:J34) -> 4.06
B37: Q5. How likely are you to recommend ICICI Bank? (0–10 → NPS)
B38: Promoters (9–10) | C38: 31 | D38: 29 | E38: 27 | F38: 25 | G38: 25 | H38: 28 | I38: 30 | J38: 31
B39: Passives (7–8) | C39: 15 | D39: 16 | E39: 17 | F39: 17 | G39: 18 | H39: 16 | I39: 15 | J39: 15
B40: Detractors (0–6) | C40: 4 | D40: 5 | E40: 6 | F40: 8 | G40: 7 | H40: 6 | I40: 5 | J40: 4
B41: Net Promoter Score (promoters % − detractors %) | C41: =(C38-C40)/SUM(C38:C40)*100 -> 54 | D41: =(D38-D40)/SUM(D38:D40)*100 -> 48 | E41: =(E38-E40)/SUM(E38:E40)*100 -> 42 | F41: =(F38-F40)/SUM(F38:F40)*100 -> 34 | G41: =(G38-G40)/SUM(G38:G40)*100 -> 36 | H41: =(H38-H40)/SUM(H38:H40)*100 -> 44 | I41: =(I38-I40)/SUM(I38:I40)*100 -> 50 | J41: =(J38-J40)/SUM(J38:J40)*100 -> 54
B43: CUSTOMER SATISFACTION INDEX (avg of Q1–Q4 ÷ 5) | C43: =AVERAGE(C11,C19,C27,C35)/5 -> 0.822 | D43: =AVERAGE(D11,D19,D27,D35)/5 -> 0.807 | E43: =AVERAGE(E11,E19,E27,E35)/5 -> 0.795 | F43: =AVERAGE(F11,F19,F27,F35)/5 -> 0.788 | G43: =AVERAGE(G11,G19,G27,G35)/5 -> 0.785 | H43: =AVERAGE(H11,H19,H27,H35)/5 -> 0.798 | I43: =AVERAGE(I11,I19,I27,I35)/5 -> 0.81 | J43: =AVERAGE(J11,J19,J27,J35)/5 -> 0.813
B44: Overall average score (out of 5) | C44: =AVERAGE(C11,C19,C27,C35) -> 4.11 | D44: =AVERAGE(D11,D19,D27,D35) -> 4.035 | E44: =AVERAGE(E11,E19,E27,E35) -> 3.975 | F44: =AVERAGE(F11,F19,F27,F35) -> 3.94 | G44: =AVERAGE(G11,G19,G27,G35) -> 3.925 | H44: =AVERAGE(H11,H19,H27,H35) -> 3.99 | I44: =AVERAGE(I11,I19,I27,I35) -> 4.05 | J44: =AVERAGE(J11,J19,J27,J35) -> 4.065
B46: How the simulated scores were generated
B47: Q1 safety: starts at 4.45, falls 0.10 per unit of default stress, rises with marketing ('safe bank' messaging).
B48: Q2 fairness: falls 0.04 per 10 bp of risk premium we charge and with stress.
B49: Q3 hardship support: rises with collections/restructuring and digital EMI-relief spend; falls most with stress.
B50: Q4 service: rises with digital & customer-support investment.
B51: Q5 NPS: driven by stress, marketing and digital spend. 50 responses per round; seeded so results are reproducible.
B53: QUESTIONNAIRE TO CIRCULATE (Google Form)
B54: Q1. How safe do you feel keeping your money with ICICI Bank?
B55: Q2. Are our loan and deposit rates fair and clearly explained?
B56: Q3. If you faced repayment difficulty, did we offer practical support?
B57: Q4. How easy is it to get a service issue resolved (app / branch / call)?
B58: Q5. How likely are you to recommend ICICI Bank? (0–10 → NPS)
... B61: Q8. One thing ICICI Bank should improve (free text)

Sheet Sources
A1: SOURCES & DATA BASIS
B3: Source | C3: Used for | D3: Status
B4: ICICI Bank – Performance Review, quarter ended 31 March 2026 (icici.bank.in news room) | C4: FY26 PAT ₹50,147 cr, NII ₹88,075 cr, deposits ₹17,94,625 cr, advances ₹15,53,893 cr, total assets ₹23,72,531 cr, GNPA 1.40%, NNPA 0.33%, PCR 75.8%, CRAR 17.18%, CET-1 16.35% | D4: Primary
B5: ICICI Bank Form 6-K, FY2026 results (SEC EDGAR, Apr 2026) | C5: FY26 results, ₹12 dividend, contingency provision ₹13,100 cr | D5: Primary
B6: ICICI Bank Q4 FY26 earnings call / investor slides (Apr 2026) – Investing.com, Yahoo Finance summaries | C6: Segment growth (retail 50.4% of loans, business banking +24.4%), CASA 41.4%, branches 7,511, slippages/recoveries/write-offs | D6: Secondary
B7: Elite Wealth – ICICI Bank Q4 FY26 result analysis | C7: FY26 opex ₹47,234 cr, provisions ₹5,380 cr, PPOP ₹71,599 cr; FY25 opex ₹42,372 cr | D7: Secondary
B8: ICICI Bank FY25 results (Apr 2025) – Business Standard coverage | C8: FY25 PAT ₹47,227 cr, deposits ₹16,10,348 cr, advances ₹13,41,766 cr, GNPA 1.67%, NNPA 0.39%, CRAR 16.55% | D8: Secondary
B9: ICICI Bank Q2 FY27 results (17 Oct 2026) – Business Standard | C9: Real context only: PAT ₹14,843 cr, NIM 4.18%, GNPA 1.20% | D9: Secondary
B10: RBI – Scheduled Commercial Banks statement, 31 Mar 2026 | C10: System deposits ₹2,62,29,916 cr (market share denominator) | D10: Primary
B11: RBI Basel III master circular | C11: Risk weights, CRAR 11.7% incl. buffers (ICICI-specific), CET-1 8.2% | D11: Regulatory
B12: Recession scenario, decisions, survey responses | C12: All simulation-period figures | D12: FICTIONAL simulation – never ICICI actuals
